{
  "Message": null,
  "Status": 0,
  "Data": [
    {
      "Cjrq": "20260123",
      "Cjsj": "143240",
      "Cjsj2": "143240",
      "Zqdm": "688679",
      "Zqmc": "通源环境",
      "Mmsm": "证券买入",
      "Cjjg": "54.5473",
      "Cjsl": "200",
      "Cjje": "10909.46",
      "Sxf": "5.00",
      "Yhs": "0.00",
      "Ghf": "0.10",
      "Zjye": "20587.20",
      "Gfye": "600",
      "Market": "HA",
      "Cjbh": "69338387",
      "Wtbh": "2134918",
      "Gddm": "A664015685",
      "Dwc": "",
      "Qqhs": null,
      "Mmlb": "B",
      "Htxh": "0802134918",
      "Wtxh": "2134918",
      "Cpbm": "",
      "Cjxh": "69338387",
      "Wtsl": "200",
      "Wtjg": "54.5600",
      "Gfbcye": "600",
      "Jsxf": "4.41",
      "Qsf": "0.00",
      "Jygf": "0.00",
      "Jsf": "0.00",
      "Zgf": "0.00",
      "Qtf": "0.00",
      "Qtfy": "0.00",
      "Zjfss": "-10914.56",
      "Syje": "20587.20",
      "Zqyjlx": "0.00000000",
      "Jsrq": "20260123",
      "Mmlb_ex": "B",
      "Mmlb_bs": "B"
    },
    {
      "Cjrq": "20260123",
      "Cjsj": "140648",
      "Cjsj2": "140648",
      "Zqdm": "688525",
      "Zqmc": "佰维存储",
      "Mmsm": "证券卖出",
      "Cjjg": "185.7300",
      "Cjsl": "200",
      "Cjje": "37146.00",
      "Sxf": "5.00",
      "Yhs": "18.57",
      "Ghf": "0.37",
      "Zjye": "31501.76",
      "Gfye": "400",
      "Market": "HA",
      "Cjbh": "62628698",
      "Wtbh": "1927743",
      "Gddm": "A664015685",
      "Dwc": "",
      "Qqhs": null,
      "Mmlb": "S",
      "Htxh": "0801927743",
      "Wtxh": "1927743",
      "Cpbm": "",
      "Cjxh": "62628698",
      "Wtsl": "200",
      "Wtjg": "185.7300",
      "Gfbcye": "400",
      "Jsxf": "2.99",
      "Qsf": "0.00",
      "Jygf": "0.00",
      "Jsf": "0.00",
      "Zgf": "0.00",
      "Qtf": "0.00",
      "Qtfy": "0.00",
      "Zjfss": "37122.06",
      "Syje": "31501.76",
      "Zqyjlx": "0.00000000",
      "Jsrq": "20260123",
      "Mmlb_ex": "S",
      "Mmlb_bs": "S"
    },
    {
      "Cjrq": "20260123",
      "Cjsj": "132801",
      "Cjsj2": "132801",
      "Zqdm": "688679",
      "Zqmc": "通源环境",
      "Mmsm": "证券买入",
      "Cjjg": "54.0900",
      "Cjsl": "200",
      "Cjje": "10818.00",
      "Sxf": "5.00",
      "Yhs": "0.00",
      "Ghf": "0.11",
      "Zjye": "-5620.30",
      "Gfye": "400",
      "Market": "HA",
      "Cjbh": "53840426",
      "Wtbh": "1736828",
      "Gddm": "A664015685",
      "Dwc": "",
      "Qqhs": null,
      "Mmlb": "B",
      "Htxh": "0801736828",
      "Wtxh": "1736828",
      "Cpbm": "",
      "Cjxh": "53840426",
      "Wtsl": "200",
      "Wtjg": "54.0900",
      "Gfbcye": "400",
      "Jsxf": "4.41",
      "Qsf": "0.00",
      "Jygf": "0.00",
      "Jsf": "0.00",
      "Zgf": "0.00",
      "Qtf": "0.00",
      "Qtfy": "0.00",
      "Zjfss": "-10823.11",
      "Syje": "-5620.30",
      "Zqyjlx": "0.00000000",
      "Jsrq": "20260123",
      "Mmlb_ex": "B",
      "Mmlb_bs": "B"
    },
    {
      "Cjrq": "20260123",
      "Cjsj": "131859",
      "Cjsj2": "131859",
      "Zqdm": "603920",
      "Zqmc": "世运电路",
      "Mmsm": "证券卖出",
      "Cjjg": "65.7100",
      "Cjsl": "500",
      "Cjje": "32855.00",
      "Sxf": "5.00",
      "Yhs": "16.43",
      "Ghf": "0.33",
      "Zjye": "5202.81",
      "Gfye": "1400",
      "Market": "HA",
      "Cjbh": "51490692",
      "Wtbh": "1698880",
      "Gddm": "A664015685",
      "Dwc": "",
      "Qqhs": null,
      "Mmlb": "S",
      "Htxh": "0801698880",
      "Wtxh": "1698880",
      "Cpbm": "",
      "Cjxh": "51490692",
      "Wtsl": "500",
      "Wtjg": "65.7100",
      "Gfbcye": "1400",
      "Jsxf": "3.22",
      "Qsf": "0.00",
      "Jygf": "0.00",
      "Jsf": "0.00",
      "Zgf": "0.00",
      "Qtf": "0.00",
      "Qtfy": "0.00",
      "Zjfss": "32833.24",
      "Syje": "5202.81",
      "Zqyjlx": "0.00000000",
      "Jsrq": "20260123",
      "Mmlb_ex": "S",
      "Mmlb_bs": "S"
    },
    {
      "Cjrq": "20260123",
      "Cjsj": "130003",
      "Cjsj2": "130003",
      "Zqdm": "688679",
      "Zqmc": "通源环境",
      "Mmsm": "证券买入",
      "Cjjg": "53.2200",
      "Cjsl": "200",
      "Cjje": "10644.00",
      "Sxf": "5.00",
      "Yhs": "0.00",
      "Ghf": "0.11",
      "Zjye": "-27630.43",
      "Gfye": "200",
      "Market": "HA",
      "Cjbh": "46334868",
      "Wtbh": "1553426",
      "Gddm": "A664015685",
      "Dwc": "",
      "Qqhs": null,
      "Mmlb": "B",
      "Htxh": "0801553426",
      "Wtxh": "1553426",
      "Cpbm": "",
      "Cjxh": "46334868",
      "Wtsl": "200",
      "Wtjg": "53.2200",
      "Gfbcye": "200",
      "Jsxf": "4.43",
      "Qsf": "0.00",
      "Jygf": "0.00",
      "Jsf": "0.00",
      "Zgf": "0.00",
      "Qtf": "0.00",
      "Qtfy": "0.00",
      "Zjfss": "-10649.11",
      "Syje": "-27630.43",
      "Zqyjlx": "0.00000000",
      "Jsrq": "20260123",
      "Mmlb_ex": "B",
      "Mmlb_bs": "B"
    },
    {
      "Cjrq": "20260123",
      "Cjsj": "112450",
      "Cjsj2": "112450",
      "Zqdm": "688122",
      "Zqmc": "西部超导",
      "Mmsm": "证券买入",
      "Cjjg": "94.8400",
      "Cjsl": "200",
      "Cjje": "18968.00",
      "Sxf": "5.00",
      "Yhs": "0.00",
      "Ghf": "0.19",
      "Zjye": "-16981.32",
      "Gfye": "400",
      "Market": "HA",
      "Cjbh": "45382423",
      "Wtbh": "1498536",
      "Gddm": "A664015685",
      "Dwc": "",
      "Qqhs": null,
      "Mmlb": "B",
      "Htxh": "0801498536",
      "Wtxh": "1498536",
      "Cpbm": "",
      "Cjxh": "45382423",
      "Wtsl": "200",
      "Wtjg": "94.8400",
      "Gfbcye": "400",
      "Jsxf": "3.97",
      "Qsf": "0.00",
      "Jygf": "0.00",
      "Jsf": "0.00",
      "Zgf": "0.00",
      "Qtf": "0.00",
      "Qtfy": "0.00",
      "Zjfss": "-18973.19",
      "Syje": "-16981.32",
      "Zqyjlx": "0.00000000",
      "Jsrq": "20260123",
      "Mmlb_ex": "B",
      "Mmlb_bs": "B"
    },
    {
      "Cjrq": "20260123",
      "Cjsj": "105439",
      "Cjsj2": "105439",
      "Zqdm": "512630",
      "Zqmc": "卫星基金",
      "Mmsm": "证券买入",
      "Cjjg": "1.7900",
      "Cjsl": "18000",
      "Cjje": "32220.00",
      "Sxf": "1.61",
      "Yhs": "0.00",
      "Ghf": "0.00",
      "Zjye": "1991.87",
      "Gfye": "18000",
      "Market": "HA",
      "Cjbh": "38366776",
      "Wtbh": "1308091",
      "Gddm": "A664015685",
      "Dwc": "",
      "Qqhs": null,
      "Mmlb": "B",
      "Htxh": "0801308091",
      "Wtxh": "1308091",
      "Cpbm": "",
      "Cjxh": "38366776",
      "Wtsl": "18000",
      "Wtjg": "1.7900",
      "Gfbcye": "18000",
      "Jsxf": "0.32",
      "Qsf": "0.00",
      "Jygf": "0.00",
      "Jsf": "0.00",
      "Zgf": "0.00",
      "Qtf": "0.00",
      "Qtfy": "0.00",
      "Zjfss": "-32221.61",
      "Syje": "1991.87",
      "Zqyjlx": "0.00000000",
      "Jsrq": "20260123",
      "Mmlb_ex": "B",
      "Mmlb_bs": "B"
    },
    {
      "Cjrq": "20260123",
      "Cjsj": "105346",
      "Cjsj2": "105346",
      "Zqdm": "688525",
      "Zqmc": "佰维存储",
      "Mmsm": "证券买入",
      "Cjjg": "183.3990",
      "Cjsl": "200",
      "Cjje": "36679.79",
      "Sxf": "5.00",
      "Yhs": "0.00",
      "Ghf": "0.37",
      "Zjye": "34213.48",
      "Gfye": "600",
      "Market": "HA",
      "Cjbh": "38177815",
      "Wtbh": "1302251",
      "Gddm": "A664015685",
      "Dwc": "",
      "Qqhs": null,
      "Mmlb": "B",
      "Htxh": "0801302251",
      "Wtxh": "1302251",
      "Cpbm": "",
      "Cjxh": "38177815",
      "Wtsl": "200",
      "Wtjg": "183.4000",
      "Gfbcye": "600",
      "Jsxf": "3.01",
      "Qsf": "0.00",
      "Jygf": "0.00",
      "Jsf": "0.00",
      "Zgf": "0.00",
      "Qtf": "0.00",
      "Qtfy": "0.00",
      "Zjfss": "-36685.16",
      "Syje": "34213.48",
      "Zqyjlx": "0.00000000",
      "Jsrq": "20260123",
      "Mmlb_ex": "B",
      "Mmlb_bs": "B"
    },
    {
      "Cjrq": "20260123",
      "Cjsj": "111416",
      "Cjsj2": "111416",
      "Zqdm": "300221",
      "Zqmc": "银禧科技",
      "Mmsm": "证券买入",
      "Cjjg": "12.5000",
      "Cjsl": "800",
      "Cjje": "10000.00",
      "Sxf": "5.00",
      "Yhs": "0.00",
      "Ghf": "0.00",
      "Zjye": "70898.64",
      "Gfye": "5800",
      "Market": "SA",
      "Cjbh": "0101000053096190",
      "Wtbh": "1280941",
      "Gddm": "0917534836",
      "Dwc": "",
      "Qqhs": null,
      "Mmlb": "B",
      "Htxh": "0801280941",
      "Wtxh": "1280941",
      "Cpbm": "",
      "Cjxh": "0101000053096190",
      "Wtsl": "800",
      "Wtjg": "12.5000",
      "Gfbcye": "5800",
      "Jsxf": "4.36",
      "Qsf": "0.00",
      "Jygf": "0.00",
      "Jsf": "0.00",
      "Zgf": "0.00",
      "Qtf": "0.00",
      "Qtfy": "0.00",
      "Zjfss": "-10005.00",
      "Syje": "70898.64",
      "Zqyjlx": "0.00000000",
      "Jsrq": "20260123",
      "Mmlb_ex": "B",
      "Mmlb_bs": "B"
    },
    {
      "Cjrq": "20260123",
      "Cjsj": "103914",
      "Cjsj2": "103914",
      "Zqdm": "688525",
      "Zqmc": "佰维存储",
      "Mmsm": "证券卖出",
      "Cjjg": "184.7091",
      "Cjsl": "600",
      "Cjje": "110825.44",
      "Sxf": "11.08",
      "Yhs": "55.41",
      "Ghf": "1.11",
      "Zjye": "80903.64",
      "Gfye": "400",
      "Market": "HA",
      "Cjbh": "34741325",
      "Wtbh": "1191821",
      "Gddm": "A664015685",
      "Dwc": "",
      "Qqhs": null,
      "Mmlb": "S",
      "Htxh": "0801191821",
      "Wtxh": "1191821",
      "Cpbm": "",
      "Cjxh": "34741325",
      "Wtsl": "600",
      "Wtjg": "184.6500",
      "Gfbcye": "400",
      "Jsxf": "5.08",
      "Qsf": "0.00",
      "Jygf": "0.00",
      "Jsf": "0.00",
      "Zgf": "0.00",
      "Qtf": "0.00",
      "Qtfy": "0.00",
      "Zjfss": "110757.84",
      "Syje": "80903.64",
      "Zqyjlx": "0.00000000",
      "Jsrq": "20260123",
      "Mmlb_ex": "S",
      "Mmlb_bs": "S"
    },
    {
      "Cjrq": "20260123",
      "Cjsj": "103211",
      "Cjsj2": "103211",
      "Zqdm": "512630",
      "Zqmc": "卫星基金",
      "Mmsm": "证券卖出",
      "Cjjg": "1.7480",
      "Cjsl": "30000",
      "Cjje": "52440.00",
      "Sxf": "2.62",
      "Yhs": "0.00",
      "Ghf": "0.00",
      "Zjye": "-29854.20",
      "Gfye": "0",
      "Market": "HA",
      "Cjbh": "32420639",
      "Wtbh": "1119955",
      "Gddm": "A664015685",
      "Dwc": "",
      "Qqhs": null,
      "Mmlb": "S",
      "Htxh": "0801119955",
      "Wtxh": "1119955",
      "Cpbm": "",
      "Cjxh": "32420639",
      "Wtsl": "30000",
      "Wtjg": "1.7480",
      "Gfbcye": "0",
      "Jsxf": "0.52",
      "Qsf": "0.00",
      "Jygf": "0.00",
      "Jsf": "0.00",
      "Zgf": "0.00",
      "Qtf": "0.00",
      "Qtfy": "0.00",
      "Zjfss": "52437.38",
      "Syje": "-29854.20",
      "Zqyjlx": "0.00000000",
      "Jsrq": "20260123",
      "Mmlb_ex": "S",
      "Mmlb_bs": "S"
    },
    {
      "Cjrq": "20260123",
      "Cjsj": "102805",
      "Cjsj2": "102805",
      "Zqdm": "300221",
      "Zqmc": "银禧科技",
      "Mmsm": "证券买入",
      "Cjjg": "12.0100",
      "Cjsl": "900",
      "Cjje": "10809.00",
      "Sxf": "5.00",
      "Yhs": "0.00",
      "Ghf": "0.00",
      "Zjye": "-82291.58",
      "Gfye": "5000",
      "Market": "SA",
      "Cjbh": "0101000037982991",
      "Wtbh": "1079391",
      "Gddm": "0917534836",
      "Dwc": "",
      "Qqhs": null,
      "Mmlb": "B",
      "Htxh": "0801079391",
      "Wtxh": "1079391",
      "Cpbm": "",
      "Cjxh": "0101000037982991",
      "Wtsl": "900",
      "Wtjg": "12.0100",
      "Gfbcye": "5000",
      "Jsxf": "4.30",
      "Qsf": "0.00",
      "Jygf": "0.00",
      "Jsf": "0.00",
      "Zgf": "0.00",
      "Qtf": "0.00",
      "Qtfy": "0.00",
      "Zjfss": "-10814.00",
      "Syje": "-82291.58",
      "Zqyjlx": "0.00000000",
      "Jsrq": "20260123",
      "Mmlb_ex": "B",
      "Mmlb_bs": "B"
    },
    {
      "Cjrq": "20260123",
      "Cjsj": "101153",
      "Cjsj2": "101153",
      "Zqdm": "300221",
      "Zqmc": "银禧科技",
      "Mmsm": "证券买入",
      "Cjjg": "12.1000",
      "Cjsl": "900",
      "Cjje": "10890.00",
      "Sxf": "5.00",
      "Yhs": "0.00",
      "Ghf": "0.00",
      "Zjye": "-71477.58",
      "Gfye": "4100",
      "Market": "SA",
      "Cjbh": "0101000031381409",
      "Wtbh": "929595",
      "Gddm": "0917534836",
      "Dwc": "",
      "Qqhs": null,
      "Mmlb": "B",
      "Htxh": "0800929595",
      "Wtxh": "929595",
      "Cpbm": "",
      "Cjxh": "0101000031381409",
      "Wtsl": "900",
      "Wtjg": "12.1000",
      "Gfbcye": "4100",
      "Jsxf": "4.30",
      "Qsf": "0.00",
      "Jygf": "0.00",
      "Jsf": "0.00",
      "Zgf": "0.00",
      "Qtf": "0.00",
      "Qtfy": "0.00",
      "Zjfss": "-10895.00",
      "Syje": "-71477.58",
      "Zqyjlx": "0.00000000",
      "Jsrq": "20260123",
      "Mmlb_ex": "B",
      "Mmlb_bs": "B"
    },
    {
      "Cjrq": "20260123",
      "Cjsj": "102537",
      "Cjsj2": "102537",
      "Zqdm": "688525",
      "Zqmc": "佰维存储",
      "Mmsm": "证券买入",
      "Cjjg": "185.0000",
      "Cjsl": "200",
      "Cjje": "37000.00",
      "Sxf": "5.00",
      "Yhs": "0.00",
      "Ghf": "0.37",
      "Zjye": "-60582.58",
      "Gfye": "1000",
      "Market": "HA",
      "Cjbh": "30333593",
      "Wtbh": "915391",
      "Gddm": "A664015685",
      "Dwc": "",
      "Qqhs": null,
      "Mmlb": "B",
      "Htxh": "0800915391",
      "Wtxh": "915391",
      "Cpbm": "",
      "Cjxh": "30333593",
      "Wtsl": "200",
      "Wtjg": "185.0000",
      "Gfbcye": "1000",
      "Jsxf": "3.00",
      "Qsf": "0.00",
      "Jygf": "0.00",
      "Jsf": "0.00",
      "Zgf": "0.00",
      "Qtf": "0.00",
      "Qtfy": "0.00",
      "Zjfss": "-37005.37",
      "Syje": "-60582.58",
      "Zqyjlx": "0.00000000",
      "Jsrq": "20260123",
      "Mmlb_ex": "B",
      "Mmlb_bs": "B"
    },
    {
      "Cjrq": "20260123",
      "Cjsj": "103344",
      "Cjsj2": "103344",
      "Zqdm": "603920",
      "Zqmc": "世运电路",
      "Mmsm": "证券买入",
      "Cjjg": "64.1300",
      "Cjsl": "400",
      "Cjje": "25652.00",
      "Sxf": "5.00",
      "Yhs": "0.00",
      "Ghf": "0.26",
      "Zjye": "-23577.21",
      "Gfye": "1900",
      "Market": "HA",
      "Cjbh": "33072712",
      "Wtbh": "907980",
      "Gddm": "A664015685",
      "Dwc": "",
      "Qqhs": null,
      "Mmlb": "B",
      "Htxh": "0800907980",
      "Wtxh": "907980",
      "Cpbm": "",
      "Cjxh": "33072712",
      "Wtsl": "400",
      "Wtjg": "64.1300",
      "Gfbcye": "1900",
      "Jsxf": "3.62",
      "Qsf": "0.00",
      "Jygf": "0.00",
      "Jsf": "0.00",
      "Zgf": "0.00",
      "Qtf": "0.00",
      "Qtfy": "0.00",
      "Zjfss": "-25657.26",
      "Syje": "-23577.21",
      "Zqyjlx": "0.00000000",
      "Jsrq": "20260123",
      "Mmlb_ex": "B",
      "Mmlb_bs": "B"
    },
    {
      "Cjrq": "20260123",
      "Cjsj": "095257",
      "Cjsj2": "095257",
      "Zqdm": "300221",
      "Zqmc": "银禧科技",
      "Mmsm": "证券买入",
      "Cjjg": "11.7800",
      "Cjsl": "900",
      "Cjje": "10602.00",
      "Sxf": "5.00",
      "Yhs": "0.00",
      "Ghf": "0.00",
      "Zjye": "2080.05",
      "Gfye": "3200",
      "Market": "SA",
      "Cjbh": "0101000021742562",
      "Wtbh": "671901",
      "Gddm": "0917534836",
      "Dwc": "",
      "Qqhs": null,
      "Mmlb": "B",
      "Htxh": "0800671901",
      "Wtxh": "671901",
      "Cpbm": "",
      "Cjxh": "0101000021742562",
      "Wtsl": "900",
      "Wtjg": "11.7800",
      "Gfbcye": "3200",
      "Jsxf": "4.32",
      "Qsf": "0.00",
      "Jygf": "0.00",
      "Jsf": "0.00",
      "Zgf": "0.00",
      "Qtf": "0.00",
      "Qtfy": "0.00",
      "Zjfss": "-10607.00",
      "Syje": "2080.05",
      "Zqyjlx": "0.00000000",
      "Jsrq": "20260123",
      "Mmlb_ex": "B",
      "Mmlb_bs": "B"
    },
    {
      "Cjrq": "20260123",
      "Cjsj": "094728",
      "Cjsj2": "094728",
      "Zqdm": "300221",
      "Zqmc": "银禧科技",
      "Mmsm": "证券买入",
      "Cjjg": "11.7000",
      "Cjsl": "500",
      "Cjje": "5850.00",
      "Sxf": "5.00",
      "Yhs": "0.00",
      "Ghf": "0.00",
      "Zjye": "12687.05",
      "Gfye": "2300",
      "Market": "SA",
      "Cjbh": "0101000018319393",
      "Wtbh": "581449",
      "Gddm": "0917534836",
      "Dwc": "",
      "Qqhs": null,
      "Mmlb": "B",
      "Htxh": "0800581449",
      "Wtxh": "581449",
      "Cpbm": "",
      "Cjxh": "0101000018319393",
      "Wtsl": "500",
      "Wtjg": "11.7000",
      "Gfbcye": "2300",
      "Jsxf": "4.63",
      "Qsf": "0.00",
      "Jygf": "0.00",
      "Jsf": "0.00",
      "Zgf": "0.00",
      "Qtf": "0.00",
      "Qtfy": "0.00",
      "Zjfss": "-5855.00",
      "Syje": "12687.05",
      "Zqyjlx": "0.00000000",
      "Jsrq": "20260123",
      "Mmlb_ex": "B",
      "Mmlb_bs": "B"
    },
    {
      "Cjrq": "20260123",
      "Cjsj": "094058",
      "Cjsj2": "094058",
      "Zqdm": "300450",
      "Zqmc": "先导智能",
      "Mmsm": "证券卖出",
      "Cjjg": "58.5955",
      "Cjsl": "1100",
      "Cjje": "64455.00",
      "Sxf": "6.45",
      "Yhs": "32.23",
      "Ghf": "0.00",
      "Zjye": "18542.05",
      "Gfye": "1700",
      "Market": "SA",
      "Cjbh": "0103000015827904",
      "Wtbh": "460154",
      "Gddm": "0917534836",
      "Dwc": "",
      "Qqhs": null,
      "Mmlb": "S",
      "Htxh": "0800460154",
      "Wtxh": "460154",
      "Cpbm": "",
      "Cjxh": "0103000015827904",
      "Wtsl": "1100",
      "Wtjg": "58.4900",
      "Gfbcye": "1700",
      "Jsxf": "2.32",
      "Qsf": "0.00",
      "Jygf": "0.00",
      "Jsf": "0.00",
      "Zgf": "0.00",
      "Qtf": "0.00",
      "Qtfy": "0.00",
      "Zjfss": "64416.32",
      "Syje": "18542.05",
      "Zqyjlx": "0.00000000",
      "Jsrq": "20260123",
      "Mmlb_ex": "S",
      "Mmlb_bs": "S"
    },
    {
      "Cjrq": "20260123",
      "Cjsj": "093834",
      "Cjsj2": "093834",
      "Zqdm": "300221",
      "Zqmc": "银禧科技",
      "Mmsm": "证券买入",
      "Cjjg": "11.7500",
      "Cjsl": "900",
      "Cjje": "10575.00",
      "Sxf": "5.00",
      "Yhs": "0.00",
      "Ghf": "0.00",
      "Zjye": "-45874.27",
      "Gfye": "1800",
      "Market": "SA",
      "Cjbh": "0101000011347847",
      "Wtbh": "393274",
      "Gddm": "0917534836",
      "Dwc": "",
      "Qqhs": null,
      "Mmlb": "B",
      "Htxh": "0800393274",
      "Wtxh": "393274",
      "Cpbm": "",
      "Cjxh": "0101000011347847",
      "Wtsl": "900",
      "Wtjg": "11.7500",
      "Gfbcye": "1800",
      "Jsxf": "4.32",
      "Qsf": "0.00",
      "Jygf": "0.00",
      "Jsf": "0.00",
      "Zgf": "0.00",
      "Qtf": "0.00",
      "Qtfy": "0.00",
      "Zjfss": "-10580.00",
      "Syje": "-45874.27",
      "Zqyjlx": "0.00000000",
      "Jsrq": "20260123",
      "Mmlb_ex": "B",
      "Mmlb_bs": "B"
    },
    {
      "Cjrq": "20260123",
      "Cjsj": "093303",
      "Cjsj2": "093303",
      "Zqdm": "300221",
      "Zqmc": "银禧科技",
      "Mmsm": "证券买入",
      "Cjjg": "11.8300",
      "Cjsl": "900",
      "Cjje": "10647.00",
      "Sxf": "5.00",
      "Yhs": "0.00",
      "Ghf": "0.00",
      "Zjye": "-35294.27",
      "Gfye": "900",
      "Market": "SA",
      "Cjbh": "0101000006061114",
      "Wtbh": "269487",
      "Gddm": "0917534836",
      "Dwc": "",
      "Qqhs": null,
      "Mmlb": "B",
      "Htxh": "0800269487",
      "Wtxh": "269487",
      "Cpbm": "",
      "Cjxh": "0101000006061114",
      "Wtsl": "900",
      "Wtjg": "11.8300",
      "Gfbcye": "900",
      "Jsxf": "4.32",
      "Qsf": "0.00",
      "Jygf": "0.00",
      "Jsf": "0.00",
      "Zgf": "0.00",
      "Qtf": "0.00",
      "Qtfy": "0.00",
      "Zjfss": "-10652.00",
      "Syje": "-35294.27",
      "Zqyjlx": "0.00000000",
      "Jsrq": "20260123",
      "Mmlb_ex": "B",
      "Mmlb_bs": "B"
    },
    {
      "Cjrq": "20260123",
      "Cjsj": "093133",
      "Cjsj2": "093133",
      "Zqdm": "002657",
      "Zqmc": "中科金财",
      "Mmsm": "证券卖出",
      "Cjjg": "30.3100",
      "Cjsl": "800",
      "Cjje": "24248.00",
      "Sxf": "5.00",
      "Yhs": "12.14",
      "Ghf": "0.00",
      "Zjye": "-24642.27",
      "Gfye": "0",
      "Market": "SA",
      "Cjbh": "0103000005328363",
      "Wtbh": "224042",
      "Gddm": "0917534836",
      "Dwc": "",
      "Qqhs": null,
      "Mmlb": "S",
      "Htxh": "0800224042",
      "Wtxh": "224042",
      "Cpbm": "",
      "Cjxh": "0103000005328363",
      "Wtsl": "800",
      "Wtjg": "30.3100",
      "Gfbcye": "0",
      "Jsxf": "3.46",
      "Qsf": "0.00",
      "Jygf": "0.00",
      "Jsf": "0.00",
      "Zgf": "0.00",
      "Qtf": "0.00",
      "Qtfy": "0.00",
      "Zjfss": "24230.86",
      "Syje": "-24642.27",
      "Zqyjlx": "0.00000000",
      "Jsrq": "20260123",
      "Mmlb_ex": "S",
      "Mmlb_bs": "S"
    },
    {
      "Cjrq": "20260123",
      "Cjsj": "092501",
      "Cjsj2": "092501",
      "Zqdm": "688122",
      "Zqmc": "西部超导",
      "Mmsm": "证券买入",
      "Cjjg": "92.0000",
      "Cjsl": "200",
      "Cjje": "18400.00",
      "Sxf": "5.00",
      "Yhs": "0.00",
      "Ghf": "0.18",
      "Zjye": "-48873.13",
      "Gfye": "200",
      "Market": "HA",
      "Cjbh": "417274",
      "Wtbh": "18036",
      "Gddm": "A664015685",
      "Dwc": "",
      "Qqhs": null,
      "Mmlb": "B",
      "Htxh": "0800018036",
      "Wtxh": "18036",
      "Cpbm": "",
      "Cjxh": "417274",
      "Wtsl": "200",
      "Wtjg": "110.2000",
      "Gfbcye": "200",
      "Jsxf": "4.00",
      "Qsf": "0.00",
      "Jygf": "0.00",
      "Jsf": "0.00",
      "Zgf": "0.00",
      "Qtf": "0.00",
      "Qtfy": "0.00",
      "Zjfss": "-18405.18",
      "Syje": "-48873.13",
      "Zqyjlx": "0.00000000",
      "Jsrq": "20260123",
      "Mmlb_ex": "B",
      "Mmlb_bs": "B"
    },
    {
      "Cjrq": "20260123",
      "Cjsj": "092500",
      "Cjsj2": "092500",
      "Zqdm": "600879",
      "Zqmc": "航天电子",
      "Mmsm": "证券买入",
      "Cjjg": "28.9000",
      "Cjsl": "700",
      "Cjje": "20230.00",
      "Sxf": "5.00",
      "Yhs": "0.00",
      "Ghf": "0.20",
      "Zjye": "-30467.95",
      "Gfye": "700",
      "Market": "HA",
      "Cjbh": "71895",
      "Wtbh": "6010",
      "Gddm": "A664015685",
      "Dwc": "",
      "Qqhs": null,
      "Mmlb": "B",
      "Htxh": "0800006010",
      "Wtxh": "6010",
      "Cpbm": "",
      "Cjxh": "71895",
      "Wtsl": "700",
      "Wtjg": "31.4600",
      "Gfbcye": "700",
      "Jsxf": "3.90",
      "Qsf": "0.00",
      "Jygf": "0.00",
      "Jsf": "0.00",
      "Zgf": "0.00",
      "Qtf": "0.00",
      "Qtfy": "0.00",
      "Zjfss": "-20235.20",
      "Syje": "-30467.95",
      "Zqyjlx": "0.00000000",
      "Jsrq": "20260123",
      "Mmlb_ex": "B",
      "Mmlb_bs": "B"
    },
    {
      "Cjrq": "20260122",
      "Cjsj": "150000",
      "Cjsj2": "150000",
      "Zqdm": "603920",
      "Zqmc": "世运电路",
      "Mmsm": "证券买入",
      "Cjjg": "59.7400",
      "Cjsl": "300",
      "Cjje": "17922.00",
      "Sxf": "5.00",
      "Yhs": "0.00",
      "Ghf": "0.18",
      "Zjye": "99881.62",
      "Gfye": "1500",
      "Market": "HA",
      "Cjbh": "71345887",
      "Wtbh": "2011624",
      "Gddm": "A664015685",
      "Dwc": "",
      "Qqhs": null,
      "Mmlb": "B",
      "Htxh": "0802011624",
      "Wtxh": "2011624",
      "Cpbm": "",
      "Cjxh": "71345887",
      "Wtsl": "300",
      "Wtjg": "59.7700",
      "Gfbcye": "1500",
      "Jsxf": "4.03",
      "Qsf": "0.00",
      "Jygf": "0.00",
      "Jsf": "0.00",
      "Zgf": "0.00",
      "Qtf": "0.00",
      "Qtfy": "0.00",
      "Zjfss": "-17927.18",
      "Syje": "99881.62",
      "Zqyjlx": "0.00000000",
      "Jsrq": "20260122",
      "Mmlb_ex": "B",
      "Mmlb_bs": "B"
    },
    {
      "Cjrq": "20260122",
      "Cjsj": "140408",
      "Cjsj2": "140408",
      "Zqdm": "603920",
      "Zqmc": "世运电路",
      "Mmsm": "证券卖出",
      "Cjjg": "59.4100",
      "Cjsl": "1000",
      "Cjje": "59410.00",
      "Sxf": "5.94",
      "Yhs": "29.70",
      "Ghf": "0.60",
      "Zjye": "117808.80",
      "Gfye": "1200",
      "Market": "HA",
      "Cjbh": "57089517",
      "Wtbh": "1678462",
      "Gddm": "A664015685",
      "Dwc": "",
      "Qqhs": null,
      "Mmlb": "S",
      "Htxh": "0801678462",
      "Wtxh": "1678462",
      "Cpbm": "",
      "Cjxh": "57089517",
      "Wtsl": "1000",
      "Wtjg": "59.4100",
      "Gfbcye": "1200",
      "Jsxf": "2.71",
      "Qsf": "0.00",
      "Jygf": "0.00",
      "Jsf": "0.00",
      "Zgf": "0.00",
      "Qtf": "0.00",
      "Qtfy": "0.00",
      "Zjfss": "59373.76",
      "Syje": "117808.80",
      "Zqyjlx": "0.00000000",
      "Jsrq": "20260122",
      "Mmlb_ex": "S",
      "Mmlb_bs": "S"
    },
    {
      "Cjrq": "20260122",
      "Cjsj": "135959",
      "Cjsj2": "135959",
      "Zqdm": "512630",
      "Zqmc": "卫星基金",
      "Mmsm": "证券买入",
      "Cjjg": "1.6640",
      "Cjsl": "30000",
      "Cjje": "49920.00",
      "Sxf": "2.50",
      "Yhs": "0.00",
      "Ghf": "0.00",
      "Zjye": "58435.04",
      "Gfye": "30000",
      "Market": "HA",
      "Cjbh": "56299268",
      "Wtbh": "1660502",
      "Gddm": "A664015685",
      "Dwc": "",
      "Qqhs": null,
      "Mmlb": "B",
      "Htxh": "0801660502",
      "Wtxh": "1660502",
      "Cpbm": "",
      "Cjxh": "56299268",
      "Wtsl": "30000",
      "Wtjg": "1.6640",
      "Gfbcye": "30000",
      "Jsxf": "0.50",
      "Qsf": "0.00",
      "Jygf": "0.00",
      "Jsf": "0.00",
      "Zgf": "0.00",
      "Qtf": "0.00",
      "Qtfy": "0.00",
      "Zjfss": "-49922.50",
      "Syje": "58435.04",
      "Zqyjlx": "0.00000000",
      "Jsrq": "20260122",
      "Mmlb_ex": "B",
      "Mmlb_bs": "B"
    },
    {
      "Cjrq": "20260122",
      "Cjsj": "135243",
      "Cjsj2": "135243",
      "Zqdm": "600160",
      "Zqmc": "巨化股份",
      "Mmsm": "证券卖出",
      "Cjjg": "39.0100",
      "Cjsl": "300",
      "Cjje": "11703.00",
      "Sxf": "5.00",
      "Yhs": "5.85",
      "Ghf": "0.12",
      "Zjye": "108357.54",
      "Gfye": "0",
      "Market": "HA",
      "Cjbh": "55122627",
      "Wtbh": "1627632",
      "Gddm": "A664015685",
      "Dwc": "",
      "Qqhs": null,
      "Mmlb": "S",
      "Htxh": "0801627632",
      "Wtxh": "1627632",
      "Cpbm": "",
      "Cjxh": "55122627",
      "Wtsl": "300",
      "Wtjg": "39.0100",
      "Gfbcye": "0",
      "Jsxf": "4.36",
      "Qsf": "0.00",
      "Jygf": "0.00",
      "Jsf": "0.00",
      "Zgf": "0.00",
      "Qtf": "0.00",
      "Qtfy": "0.00",
      "Zjfss": "11692.03",
      "Syje": "108357.54",
      "Zqyjlx": "0.00000000",
      "Jsrq": "20260122",
      "Mmlb_ex": "S",
      "Mmlb_bs": "S"
    },
    {
      "Cjrq": "20260122",
      "Cjsj": "135149",
      "Cjsj2": "135149",
      "Zqdm": "300450",
      "Zqmc": "先导智能",
      "Mmsm": "证券买入",
      "Cjjg": "57.2200",
      "Cjsl": "200",
      "Cjje": "11444.00",
      "Sxf": "5.00",
      "Yhs": "0.00",
      "Ghf": "0.00",
      "Zjye": "96665.51",
      "Gfye": "2800",
      "Market": "SA",
      "Cjbh": "0103000061327851",
      "Wtbh": "1615990",
      "Gddm": "0917534836",
      "Dwc": "",
      "Qqhs": null,
      "Mmlb": "B",
      "Htxh": "0801615990",
      "Wtxh": "1615990",
      "Cpbm": "",
      "Cjxh": "0103000061327851",
      "Wtsl": "200",
      "Wtjg": "57.2200",
      "Gfbcye": "2800",
      "Jsxf": "4.27",
      "Qsf": "0.00",
      "Jygf": "0.00",
      "Jsf": "0.00",
      "Zgf": "0.00",
      "Qtf": "0.00",
      "Qtfy": "0.00",
      "Zjfss": "-11449.00",
      "Syje": "96665.51",
      "Zqyjlx": "0.00000000",
      "Jsrq": "20260122",
      "Mmlb_ex": "B",
      "Mmlb_bs": "B"
    },
    {
      "Cjrq": "20260122",
      "Cjsj": "130534",
      "Cjsj2": "130534",
      "Zqdm": "603920",
      "Zqmc": "世运电路",
      "Mmsm": "证券买入",
      "Cjjg": "58.8900",
      "Cjsl": "800",
      "Cjje": "47112.00",
      "Sxf": "5.00",
      "Yhs": "0.00",
      "Ghf": "0.47",
      "Zjye": "108114.51",
      "Gfye": "2200",
      "Market": "HA",
      "Cjbh": "46445417",
      "Wtbh": "1406136",
      "Gddm": "A664015685",
      "Dwc": "",
      "Qqhs": null,
      "Mmlb": "B",
      "Htxh": "0801406136",
      "Wtxh": "1406136",
      "Cpbm": "",
      "Cjxh": "46445417",
      "Wtsl": "800",
      "Wtjg": "58.8900",
      "Gfbcye": "2200",
      "Jsxf": "2.45",
      "Qsf": "0.00",
      "Jygf": "0.00",
      "Jsf": "0.00",
      "Zgf": "0.00",
      "Qtf": "0.00",
      "Qtfy": "0.00",
      "Zjfss": "-47117.47",
      "Syje": "108114.51",
      "Zqyjlx": "0.00000000",
      "Jsrq": "20260122",
      "Mmlb_ex": "B",
      "Mmlb_bs": "B"
    },
    {
      "Cjrq": "20260122",
      "Cjsj": "112933",
      "Cjsj2": "112933",
      "Zqdm": "300450",
      "Zqmc": "先导智能",
      "Mmsm": "证券买入",
      "Cjjg": "57.5600",
      "Cjsl": "200",
      "Cjje": "11512.00",
      "Sxf": "5.00",
      "Yhs": "0.00",
      "Ghf": "0.00",
      "Zjye": "155231.98",
      "Gfye": "2600",
      "Market": "SA",
      "Cjbh": "0103000049605712",
      "Wtbh": "1339257",
      "Gddm": "0917534836",
      "Dwc": "",
      "Qqhs": null,
      "Mmlb": "B",
      "Htxh": "0801339257",
      "Wtxh": "1339257",
      "Cpbm": "",
      "Cjxh": "0103000049605712",
      "Wtsl": "200",
      "Wtjg": "57.5800",
      "Gfbcye": "2600",
      "Jsxf": "4.26",
      "Qsf": "0.00",
      "Jygf": "0.00",
      "Jsf": "0.00",
      "Zgf": "0.00",
      "Qtf": "0.00",
      "Qtfy": "0.00",
      "Zjfss": "-11517.00",
      "Syje": "155231.98",
      "Zqyjlx": "0.00000000",
      "Jsrq": "20260122",
      "Mmlb_ex": "B",
      "Mmlb_bs": "B"
    },
    {
      "Cjrq": "20260122",
      "Cjsj": "110131",
      "Cjsj2": "110131",
      "Zqdm": "603920",
      "Zqmc": "世运电路",
      "Mmsm": "证券卖出",
      "Cjjg": "59.5500",
      "Cjsl": "200",
      "Cjje": "11910.00",
      "Sxf": "5.00",
      "Yhs": "5.96",
      "Ghf": "0.12",
      "Zjye": "166748.98",
      "Gfye": "1400",
      "Market": "HA",
      "Cjbh": "39163918",
      "Wtbh": "1208108",
      "Gddm": "A664015685",
      "Dwc": "",
      "Qqhs": null,
      "Mmlb": "S",
      "Htxh": "0801208108",
      "Wtxh": "1208108",
      "Cpbm": "",
      "Cjxh": "39163918",
      "Wtsl": "200",
      "Wtjg": "59.5500",
      "Gfbcye": "1400",
      "Jsxf": "4.35",
      "Qsf": "0.00",
      "Jygf": "0.00",
      "Jsf": "0.00",
      "Zgf": "0.00",
      "Qtf": "0.00",
      "Qtfy": "0.00",
      "Zjfss": "11898.92",
      "Syje": "166748.98",
      "Zqyjlx": "0.00000000",
      "Jsrq": "20260122",
      "Mmlb_ex": "S",
      "Mmlb_bs": "S"
    },
    {
      "Cjrq": "20260122",
      "Cjsj": "104757",
      "Cjsj2": "104757",
      "Zqdm": "688525",
      "Zqmc": "佰维存储",
      "Mmsm": "证券卖出",
      "Cjjg": "190.5500",
      "Cjsl": "500",
      "Cjje": "95275.00",
      "Sxf": "9.53",
      "Yhs": "47.64",
      "Ghf": "0.95",
      "Zjye": "154850.06",
      "Gfye": "800",
      "Market": "HA",
      "Cjbh": "36384849",
      "Wtbh": "1145616",
      "Gddm": "A664015685",
      "Dwc": "",
      "Qqhs": null,
      "Mmlb": "S",
      "Htxh": "0801145616",
      "Wtxh": "1145616",
      "Cpbm": "",
      "Cjxh": "36384849",
      "Wtsl": "500",
      "Wtjg": "190.5500",
      "Gfbcye": "800",
      "Jsxf": "4.37",
      "Qsf": "0.00",
      "Jygf": "0.00",
      "Jsf": "0.00",
      "Zgf": "0.00",
      "Qtf": "0.00",
      "Qtfy": "0.00",
      "Zjfss": "95216.88",
      "Syje": "154850.06",
      "Zqyjlx": "0.00000000",
      "Jsrq": "20260122",
      "Mmlb_ex": "S",
      "Mmlb_bs": "S"
    },
    {
      "Cjrq": "20260122",
      "Cjsj": "101726",
      "Cjsj2": "101726",
      "Zqdm": "300450",
      "Zqmc": "先导智能",
      "Mmsm": "证券买入",
      "Cjjg": "58.0500",
      "Cjsl": "400",
      "Cjje": "23220.00",
      "Sxf": "5.00",
      "Yhs": "0.00",
      "Ghf": "0.00",
      "Zjye": "59633.18",
      "Gfye": "2400",
      "Market": "SA",
      "Cjbh": "0103000030760064",
      "Wtbh": "913933",
      "Gddm": "0917534836",
      "Dwc": "",
      "Qqhs": null,
      "Mmlb": "B",
      "Htxh": "0800913933",
      "Wtxh": "913933",
      "Cpbm": "",
      "Cjxh": "0103000030760064",
      "Wtsl": "400",
      "Wtjg": "58.0500",
      "Gfbcye": "2400",
      "Jsxf": "3.52",
      "Qsf": "0.00",
      "Jygf": "0.00",
      "Jsf": "0.00",
      "Zgf": "0.00",
      "Qtf": "0.00",
      "Qtfy": "0.00",
      "Zjfss": "-23225.00",
      "Syje": "59633.18",
      "Zqyjlx": "0.00000000",
      "Jsrq": "20260122",
      "Mmlb_ex": "B",
      "Mmlb_bs": "B"
    },
    {
      "Cjrq": "20260122",
      "Cjsj": "105416",
      "Cjsj2": "105416",
      "Zqdm": "688525",
      "Zqmc": "佰维存储",
      "Mmsm": "证券卖出",
      "Cjjg": "193.5300",
      "Cjsl": "300",
      "Cjje": "58059.00",
      "Sxf": "5.81",
      "Yhs": "29.03",
      "Ghf": "0.58",
      "Zjye": "82858.18",
      "Gfye": "1300",
      "Market": "HA",
      "Cjbh": "37816667",
      "Wtbh": "718741",
      "Gddm": "A664015685",
      "Dwc": "",
      "Qqhs": null,
      "Mmlb": "S",
      "Htxh": "0800718741",
      "Wtxh": "718741",
      "Cpbm": "",
      "Cjxh": "37816667",
      "Wtsl": "300",
      "Wtjg": "193.5300",
      "Gfbcye": "1300",
      "Jsxf": "2.67",
      "Qsf": "0.00",
      "Jygf": "0.00",
      "Jsf": "0.00",
      "Zgf": "0.00",
      "Qtf": "0.00",
      "Qtfy": "0.00",
      "Zjfss": "58023.58",
      "Syje": "82858.18",
      "Zqyjlx": "0.00000000",
      "Jsrq": "20260122",
      "Mmlb_ex": "S",
      "Mmlb_bs": "S"
    },
    {
      "Cjrq": "20260122",
      "Cjsj": "100032",
      "Cjsj2": "100032",
      "Zqdm": "688525",
      "Zqmc": "佰维存储",
      "Mmsm": "证券买入",
      "Cjjg": "183.8900",
      "Cjsl": "200",
      "Cjje": "36778.00",
      "Sxf": "5.00",
      "Yhs": "0.00",
      "Ghf": "0.37",
      "Zjye": "24834.60",
      "Gfye": "1600",
      "Market": "HA",
      "Cjbh": "20650304",
      "Wtbh": "669809",
      "Gddm": "A664015685",
      "Dwc": "",
      "Qqhs": null,
      "Mmlb": "B",
      "Htxh": "0800669809",
      "Wtxh": "669809",
      "Cpbm": "",
      "Cjxh": "20650304",
      "Wtsl": "200",
      "Wtjg": "183.8900",
      "Gfbcye": "1600",
      "Jsxf": "3.01",
      "Qsf": "0.00",
      "Jygf": "0.00",
      "Jsf": "0.00",
      "Zgf": "0.00",
      "Qtf": "0.00",
      "Qtfy": "0.00",
      "Zjfss": "-36783.37",
      "Syje": "24834.60",
      "Zqyjlx": "0.00000000",
      "Jsrq": "20260122",
      "Mmlb_ex": "B",
      "Mmlb_bs": "B"
    },
    {
      "Cjrq": "20260122",
      "Cjsj": "095446",
      "Cjsj2": "095446",
      "Zqdm": "603920",
      "Zqmc": "世运电路",
      "Mmsm": "证券买入",
      "Cjjg": "58.5100",
      "Cjsl": "400",
      "Cjje": "23404.00",
      "Sxf": "5.00",
      "Yhs": "0.00",
      "Ghf": "0.23",
      "Zjye": "61617.97",
      "Gfye": "1600",
      "Market": "HA",
      "Cjbh": "18152838",
      "Wtbh": "640194",
      "Gddm": "A664015685",
      "Dwc": "",
      "Qqhs": null,
      "Mmlb": "B",
      "Htxh": "0800640194",
      "Wtxh": "640194",
      "Cpbm": "",
      "Cjxh": "18152838",
      "Wtsl": "400",
      "Wtjg": "58.5600",
      "Gfbcye": "1600",
      "Jsxf": "3.73",
      "Qsf": "0.00",
      "Jygf": "0.00",
      "Jsf": "0.00",
      "Zgf": "0.00",
      "Qtf": "0.00",
      "Qtfy": "0.00",
      "Zjfss": "-23409.23",
      "Syje": "61617.97",
      "Zqyjlx": "0.00000000",
      "Jsrq": "20260122",
      "Mmlb_ex": "B",
      "Mmlb_bs": "B"
    },
    {
      "Cjrq": "20260122",
      "Cjsj": "095031",
      "Cjsj2": "095031",
      "Zqdm": "688525",
      "Zqmc": "佰维存储",
      "Mmsm": "证券买入",
      "Cjjg": "186.2927",
      "Cjsl": "300",
      "Cjje": "55887.80",
      "Sxf": "5.59",
      "Yhs": "0.00",
      "Ghf": "0.56",
      "Zjye": "85027.20",
      "Gfye": "1400",
      "Market": "HA",
      "Cjbh": "16219638",
      "Wtbh": "580121",
      "Gddm": "A664015685",
      "Dwc": "",
      "Qqhs": null,
      "Mmlb": "B",
      "Htxh": "0800580121",
      "Wtxh": "580121",
      "Cpbm": "",
      "Cjxh": "16219638",
      "Wtsl": "300",
      "Wtjg": "186.3600",
      "Gfbcye": "1400",
      "Jsxf": "2.57",
      "Qsf": "0.00",
      "Jygf": "0.00",
      "Jsf": "0.00",
      "Zgf": "0.00",
      "Qtf": "0.00",
      "Qtfy": "0.00",
      "Zjfss": "-55893.95",
      "Syje": "85027.20",
      "Zqyjlx": "0.00000000",
      "Jsrq": "20260122",
      "Mmlb_ex": "B",
      "Mmlb_bs": "B"
    },
    {
      "Cjrq": "20260122",
      "Cjsj": "095502",
      "Cjsj2": "095502",
      "Zqdm": "688525",
      "Zqmc": "佰维存储",
      "Mmsm": "证券买入",
      "Cjjg": "183.6700",
      "Cjsl": "300",
      "Cjje": "55101.00",
      "Sxf": "5.51",
      "Yhs": "0.00",
      "Ghf": "0.55",
      "Zjye": "140921.15",
      "Gfye": "1100",
      "Market": "HA",
      "Cjbh": "18278272",
      "Wtbh": "477803",
      "Gddm": "A664015685",
      "Dwc": "",
      "Qqhs": null,
      "Mmlb": "B",
      "Htxh": "0800477803",
      "Wtxh": "477803",
      "Cpbm": "",
      "Cjxh": "18278272",
      "Wtsl": "300",
      "Wtjg": "183.6700",
      "Gfbcye": "1100",
      "Jsxf": "2.53",
      "Qsf": "0.00",
      "Jygf": "0.00",
      "Jsf": "0.00",
      "Zgf": "0.00",
      "Qtf": "0.00",
      "Qtfy": "0.00",
      "Zjfss": "-55107.06",
      "Syje": "140921.15",
      "Zqyjlx": "0.00000000",
      "Jsrq": "20260122",
      "Mmlb_ex": "B",
      "Mmlb_bs": "B"
    },
    {
      "Cjrq": "20260122",
      "Cjsj": "094650",
      "Cjsj2": "094650",
      "Zqdm": "300450",
      "Zqmc": "先导智能",
      "Mmsm": "证券买入",
      "Cjjg": "58.6000",
      "Cjsl": "400",
      "Cjje": "23440.00",
      "Sxf": "5.00",
      "Yhs": "0.00",
      "Ghf": "0.00",
      "Zjye": "196028.21",
      "Gfye": "2000",
      "Market": "SA",
      "Cjbh": "0103000016189121",
      "Wtbh": "459773",
      "Gddm": "0917534836",
      "Dwc": "",
      "Qqhs": null,
      "Mmlb": "B",
      "Htxh": "0800459773",
      "Wtxh": "459773",
      "Cpbm": "",
      "Cjxh": "0103000016189121",
      "Wtsl": "400",
      "Wtjg": "58.6000",
      "Gfbcye": "2000",
      "Jsxf": "3.50",
      "Qsf": "0.00",
      "Jygf": "0.00",
      "Jsf": "0.00",
      "Zgf": "0.00",
      "Qtf": "0.00",
      "Qtfy": "0.00",
      "Zjfss": "-23445.00",
      "Syje": "196028.21",
      "Zqyjlx": "0.00000000",
      "Jsrq": "20260122",
      "Mmlb_ex": "B",
      "Mmlb_bs": "B"
    },
    {
      "Cjrq": "20260122",
      "Cjsj": "093001",
      "Cjsj2": "093001",
      "Zqdm": "002657",
      "Zqmc": "中科金财",
      "Mmsm": "证券买入",
      "Cjjg": "30.5800",
      "Cjsl": "700",
      "Cjje": "21406.00",
      "Sxf": "5.00",
      "Yhs": "0.00",
      "Ghf": "0.00",
      "Zjye": "219473.21",
      "Gfye": "800",
      "Market": "SA",
      "Cjbh": "0102000001400801",
      "Wtbh": "128110",
      "Gddm": "0917534836",
      "Dwc": "",
      "Qqhs": null,
      "Mmlb": "B",
      "Htxh": "0800128110",
      "Wtxh": "128110",
      "Cpbm": "",
      "Cjxh": "0102000001400801",
      "Wtsl": "700",
      "Wtjg": "30.6000",
      "Gfbcye": "800",
      "Jsxf": "3.63",
      "Qsf": "0.00",
      "Jygf": "0.00",
      "Jsf": "0.00",
      "Zgf": "0.00",
      "Qtf": "0.00",
      "Qtfy": "0.00",
      "Zjfss": "-21411.00",
      "Syje": "219473.21",
      "Zqyjlx": "0.00000000",
      "Jsrq": "20260122",
      "Mmlb_ex": "B",
      "Mmlb_bs": "B"
    },
    {
      "Cjrq": "20260121",
      "Cjsj": "145535",
      "Cjsj2": "145535",
      "Zqdm": "002657",
      "Zqmc": "中科金财",
      "Mmsm": "证券买入",
      "Cjjg": "30.2400",
      "Cjsl": "100",
      "Cjje": "3024.00",
      "Sxf": "5.00",
      "Yhs": "0.00",
      "Ghf": "0.00",
      "Zjye": "59556.63",
      "Gfye": "100",
      "Market": "SA",
      "Cjbh": "0105000082695605",
      "Wtbh": "1901960",
      "Gddm": "0917534836",
      "Dwc": "",
      "Qqhs": null,
      "Mmlb": "B",
      "Htxh": "0801901960",
      "Wtxh": "1901960",
      "Cpbm": "",
      "Cjxh": "0105000082695605",
      "Wtsl": "100",
      "Wtjg": "30.2400",
      "Gfbcye": "100",
      "Jsxf": "4.81",
      "Qsf": "0.00",
      "Jygf": "0.00",
      "Jsf": "0.00",
      "Zgf": "0.00",
      "Qtf": "0.00",
      "Qtfy": "0.00",
      "Zjfss": "-3029.00",
      "Syje": "59556.63",
      "Zqyjlx": "0.00000000",
      "Jsrq": "20260121",
      "Mmlb_ex": "B",
      "Mmlb_bs": "B"
    },
    {
      "Cjrq": "20260121",
      "Cjsj": "144324",
      "Cjsj2": "144324",
      "Zqdm": "600160",
      "Zqmc": "巨化股份",
      "Mmsm": "证券买入",
      "Cjjg": "40.0000",
      "Cjsl": "300",
      "Cjje": "12000.00",
      "Sxf": "5.00",
      "Yhs": "0.00",
      "Ghf": "0.12",
      "Zjye": "62585.63",
      "Gfye": "300",
      "Market": "HA",
      "Cjbh": "66507088",
      "Wtbh": "1793255",
      "Gddm": "A664015685",
      "Dwc": "",
      "Qqhs": null,
      "Mmlb": "B",
      "Htxh": "0801793255",
      "Wtxh": "1793255",
      "Cpbm": "",
      "Cjxh": "66507088",
      "Wtsl": "300",
      "Wtjg": "40.0000",
      "Gfbcye": "300",
      "Jsxf": "4.35",
      "Qsf": "0.00",
      "Jygf": "0.00",
      "Jsf": "0.00",
      "Zgf": "0.00",
      "Qtf": "0.00",
      "Qtfy": "0.00",
      "Zjfss": "-12005.12",
      "Syje": "62585.63",
      "Zqyjlx": "0.00000000",
      "Jsrq": "20260121",
      "Mmlb_ex": "B",
      "Mmlb_bs": "B"
    },
    {
      "Cjrq": "20260121",
      "Cjsj": "133752",
      "Cjsj2": "133752",
      "Zqdm": "603920",
      "Zqmc": "世运电路",
      "Mmsm": "证券买入",
      "Cjjg": "61.5100",
      "Cjsl": "200",
      "Cjje": "12302.00",
      "Sxf": "5.00",
      "Yhs": "0.00",
      "Ghf": "0.12",
      "Zjye": "74590.75",
      "Gfye": "1200",
      "Market": "HA",
      "Cjbh": "51371323",
      "Wtbh": "1477307",
      "Gddm": "A664015685",
      "Dwc": "",
      "Qqhs": null,
      "Mmlb": "B",
      "Htxh": "0801477307",
      "Wtxh": "1477307",
      "Cpbm": "",
      "Cjxh": "51371323",
      "Wtsl": "200",
      "Wtjg": "61.5100",
      "Gfbcye": "1200",
      "Jsxf": "4.33",
      "Qsf": "0.00",
      "Jygf": "0.00",
      "Jsf": "0.00",
      "Zgf": "0.00",
      "Qtf": "0.00",
      "Qtfy": "0.00",
      "Zjfss": "-12307.12",
      "Syje": "74590.75",
      "Zqyjlx": "0.00000000",
      "Jsrq": "20260121",
      "Mmlb_ex": "B",
      "Mmlb_bs": "B"
    },
    {
      "Cjrq": "20260121",
      "Cjsj": "132818",
      "Cjsj2": "132818",
      "Zqdm": "688525",
      "Zqmc": "佰维存储",
      "Mmsm": "证券卖出",
      "Cjjg": "193.0000",
      "Cjsl": "400",
      "Cjje": "77200.00",
      "Sxf": "7.72",
      "Yhs": "38.60",
      "Ghf": "0.77",
      "Zjye": "86897.87",
      "Gfye": "800",
      "Market": "HA",
      "Cjbh": "49340074",
      "Wtbh": "1279669",
      "Gddm": "A664015685",
      "Dwc": "",
      "Qqhs": null,
      "Mmlb": "S",
      "Htxh": "0801279669",
      "Wtxh": "1279669",
      "Cpbm": "",
      "Cjxh": "49340074",
      "Wtsl": "400",
      "Wtjg": "193.0000",
      "Gfbcye": "800",
      "Jsxf": "3.55",
      "Qsf": "0.00",
      "Jygf": "0.00",
      "Jsf": "0.00",
      "Zgf": "0.00",
      "Qtf": "0.00",
      "Qtfy": "0.00",
      "Zjfss": "77152.91",
      "Syje": "86897.87",
      "Zqyjlx": "0.00000000",
      "Jsrq": "20260121",
      "Mmlb_ex": "S",
      "Mmlb_bs": "S"
    },
    {
      "Cjrq": "20260121",
      "Cjsj": "102156",
      "Cjsj2": "102156",
      "Zqdm": "603920",
      "Zqmc": "世运电路",
      "Mmsm": "证券卖出",
      "Cjjg": "60.6500",
      "Cjsl": "1000",
      "Cjje": "60650.00",
      "Sxf": "6.07",
      "Yhs": "30.33",
      "Ghf": "0.61",
      "Zjye": "9744.96",
      "Gfye": "1000",
      "Market": "HA",
      "Cjbh": "27389426",
      "Wtbh": "837906",
      "Gddm": "A664015685",
      "Dwc": "",
      "Qqhs": null,
      "Mmlb": "S",
      "Htxh": "0800837906",
      "Wtxh": "837906",
      "Cpbm": "",
      "Cjxh": "27389426",
      "Wtsl": "1000",
      "Wtjg": "60.6500",
      "Gfbcye": "1000",
      "Jsxf": "2.79",
      "Qsf": "0.00",
      "Jygf": "0.00",
      "Jsf": "0.00",
      "Zgf": "0.00",
      "Qtf": "0.00",
      "Qtfy": "0.00",
      "Zjfss": "60612.99",
      "Syje": "9744.96",
      "Zqyjlx": "0.00000000",
      "Jsrq": "20260121",
      "Mmlb_ex": "S",
      "Mmlb_bs": "S"
    },
    {
      "Cjrq": "20260121",
      "Cjsj": "095344",
      "Cjsj2": "095344",
      "Zqdm": "688525",
      "Zqmc": "佰维存储",
      "Mmsm": "证券买入",
      "Cjjg": "190.3600",
      "Cjsl": "200",
      "Cjje": "38072.00",
      "Sxf": "5.00",
      "Yhs": "0.00",
      "Ghf": "0.38",
      "Zjye": "-50868.03",
      "Gfye": "1200",
      "Market": "HA",
      "Cjbh": "17517125",
      "Wtbh": "569599",
      "Gddm": "A664015685",
      "Dwc": "",
      "Qqhs": null,
      "Mmlb": "B",
      "Htxh": "0800569599",
      "Wtxh": "569599",
      "Cpbm": "",
      "Cjxh": "17517125",
      "Wtsl": "200",
      "Wtjg": "190.3600",
      "Gfbcye": "1200",
      "Jsxf": "2.94",
      "Qsf": "0.00",
      "Jygf": "0.00",
      "Jsf": "0.00",
      "Zgf": "0.00",
      "Qtf": "0.00",
      "Qtfy": "0.00",
      "Zjfss": "-38077.38",
      "Syje": "-50868.03",
      "Zqyjlx": "0.00000000",
      "Jsrq": "20260121",
      "Mmlb_ex": "B",
      "Mmlb_bs": "B"
    },
    {
      "Cjrq": "20260121",
      "Cjsj": "094955",
      "Cjsj2": "094955",
      "Zqdm": "603920",
      "Zqmc": "世运电路",
      "Mmsm": "证券买入",
      "Cjjg": "60.0600",
      "Cjsl": "500",
      "Cjje": "30030.00",
      "Sxf": "5.00",
      "Yhs": "0.00",
      "Ghf": "0.30",
      "Zjye": "-12790.65",
      "Gfye": "2000",
      "Market": "HA",
      "Cjbh": "15743874",
      "Wtbh": "518953",
      "Gddm": "A664015685",
      "Dwc": "",
      "Qqhs": null,
      "Mmlb": "B",
      "Htxh": "0800518953",
      "Wtxh": "518953",
      "Cpbm": "",
      "Cjxh": "15743874",
      "Wtsl": "500",
      "Wtjg": "60.0600",
      "Gfbcye": "2000",
      "Jsxf": "3.38",
      "Qsf": "0.00",
      "Jygf": "0.00",
      "Jsf": "0.00",
      "Zgf": "0.00",
      "Qtf": "0.00",
      "Qtfy": "0.00",
      "Zjfss": "-30035.30",
      "Syje": "-12790.65",
      "Zqyjlx": "0.00000000",
      "Jsrq": "20260121",
      "Mmlb_ex": "B",
      "Mmlb_bs": "B"
    },
    {
      "Cjrq": "20260121",
      "Cjsj": "094628",
      "Cjsj2": "094628",
      "Zqdm": "688525",
      "Zqmc": "佰维存储",
      "Mmsm": "证券买入",
      "Cjjg": "190.0000",
      "Cjsl": "200",
      "Cjje": "38000.00",
      "Sxf": "5.00",
      "Yhs": "0.00",
      "Ghf": "0.38",
      "Zjye": "17244.65",
      "Gfye": "1000",
      "Market": "HA",
      "Cjbh": "13998069",
      "Wtbh": "444049",
      "Gddm": "A664015685",
      "Dwc": "",
      "Qqhs": null,
      "Mmlb": "B",
      "Htxh": "0800444049",
      "Wtxh": "444049",
      "Cpbm": "",
      "Cjxh": "13998069",
      "Wtsl": "200",
      "Wtjg": "190.0000",
      "Gfbcye": "1000",
      "Jsxf": "2.94",
      "Qsf": "0.00",
      "Jygf": "0.00",
      "Jsf": "0.00",
      "Zgf": "0.00",
      "Qtf": "0.00",
      "Qtfy": "0.00",
      "Zjfss": "-38005.38",
      "Syje": "17244.65",
      "Zqyjlx": "0.00000000",
      "Jsrq": "20260121",
      "Mmlb_ex": "B",
      "Mmlb_bs": "B"
    },
    {
      "Cjrq": "20260121",
      "Cjsj": "094259",
      "Cjsj2": "094259",
      "Zqdm": "002657",
      "Zqmc": "中科金财",
      "Mmsm": "证券卖出",
      "Cjjg": "30.2900",
      "Cjsl": "1500",
      "Cjje": "45435.00",
      "Sxf": "5.00",
      "Yhs": "22.71",
      "Ghf": "0.00",
      "Zjye": "55250.03",
      "Gfye": "0",
      "Market": "SA",
      "Cjbh": "0105000014241028",
      "Wtbh": "420689",
      "Gddm": "0917534836",
      "Dwc": "",
      "Qqhs": null,
      "Mmlb": "S",
      "Htxh": "0800420689",
      "Wtxh": "420689",
      "Cpbm": "",
      "Cjxh": "0105000014241028",
      "Wtsl": "1500",
      "Wtjg": "30.2800",
      "Gfbcye": "0",
      "Jsxf": "2.10",
      "Qsf": "0.00",
      "Jygf": "0.00",
      "Jsf": "0.00",
      "Zgf": "0.00",
      "Qtf": "0.00",
      "Qtfy": "0.00",
      "Zjfss": "45407.29",
      "Syje": "55250.03",
      "Zqyjlx": "0.00000000",
      "Jsrq": "20260121",
      "Mmlb_ex": "S",
      "Mmlb_bs": "S"
    },
    {
      "Cjrq": "20260121",
      "Cjsj": "093805",
      "Cjsj2": "093805",
      "Zqdm": "300450",
      "Zqmc": "先导智能",
      "Mmsm": "证券卖出",
      "Cjjg": "57.2620",
      "Cjsl": "1500",
      "Cjje": "85893.00",
      "Sxf": "8.59",
      "Yhs": "42.93",
      "Ghf": "0.00",
      "Zjye": "9842.74",
      "Gfye": "1600",
      "Market": "SA",
      "Cjbh": "0105000010251793",
      "Wtbh": "338031",
      "Gddm": "0917534836",
      "Dwc": "",
      "Qqhs": null,
      "Mmlb": "S",
      "Htxh": "0800338031",
      "Wtxh": "338031",
      "Cpbm": "",
      "Cjxh": "0105000010251793",
      "Wtsl": "1500",
      "Wtjg": "57.2100",
      "Gfbcye": "1600",
      "Jsxf": "3.06",
      "Qsf": "0.00",
      "Jygf": "0.00",
      "Jsf": "0.00",
      "Zgf": "0.00",
      "Qtf": "0.00",
      "Qtfy": "0.00",
      "Zjfss": "85841.48",
      "Syje": "9842.74",
      "Zqyjlx": "0.00000000",
      "Jsrq": "20260121",
      "Mmlb_ex": "S",
      "Mmlb_bs": "S"
    },
    {
      "Cjrq": "20260121",
      "Cjsj": "093849",
      "Cjsj2": "093849",
      "Zqdm": "688525",
      "Zqmc": "佰维存储",
      "Mmsm": "证券买入",
      "Cjjg": "195.6100",
      "Cjsl": "200",
      "Cjje": "39122.00",
      "Sxf": "5.00",
      "Yhs": "0.00",
      "Ghf": "0.39",
      "Zjye": "-75998.74",
      "Gfye": "800",
      "Market": "HA",
      "Cjbh": "8924126",
      "Wtbh": "313750",
      "Gddm": "A664015685",
      "Dwc": "",
      "Qqhs": null,
      "Mmlb": "B",
      "Htxh": "0800313750",
      "Wtxh": "313750",
      "Cpbm": "",
      "Cjxh": "8924126",
      "Wtsl": "200",
      "Wtjg": "195.6100",
      "Gfbcye": "800",
      "Jsxf": "2.89",
      "Qsf": "0.00",
      "Jygf": "0.00",
      "Jsf": "0.00",
      "Zgf": "0.00",
      "Qtf": "0.00",
      "Qtfy": "0.00",
      "Zjfss": "-39127.39",
      "Syje": "-75998.74",
      "Zqyjlx": "0.00000000",
      "Jsrq": "20260121",
      "Mmlb_ex": "B",
      "Mmlb_bs": "B"
    },
    {
      "Cjrq": "20260121",
      "Cjsj": "093001",
      "Cjsj2": "093001",
      "Zqdm": "603920",
      "Zqmc": "世运电路",
      "Mmsm": "证券买入",
      "Cjjg": "58.0000",
      "Cjsl": "500",
      "Cjje": "29000.00",
      "Sxf": "5.00",
      "Yhs": "0.00",
      "Ghf": "0.29",
      "Zjye": "-36871.35",
      "Gfye": "1500",
      "Market": "HA",
      "Cjbh": "423844",
      "Wtbh": "114885",
      "Gddm": "A664015685",
      "Dwc": "",
      "Qqhs": null,
      "Mmlb": "B",
      "Htxh": "0800114885",
      "Wtxh": "114885",
      "Cpbm": "",
      "Cjxh": "423844",
      "Wtsl": "500",
      "Wtjg": "58.0000",
      "Gfbcye": "1500",
      "Jsxf": "3.43",
      "Qsf": "0.00",
      "Jygf": "0.00",
      "Jsf": "0.00",
      "Zgf": "0.00",
      "Qtf": "0.00",
      "Qtfy": "0.00",
      "Zjfss": "-29005.29",
      "Syje": "-36871.35",
      "Zqyjlx": "0.00000000",
      "Jsrq": "20260121",
      "Mmlb_ex": "B",
      "Mmlb_bs": "B"
    },
    {
      "Cjrq": "20260120",
      "Cjsj": "145026",
      "Cjsj2": "145026",
      "Zqdm": "688525",
      "Zqmc": "佰维存储",
      "Mmsm": "证券卖出",
      "Cjjg": "190.0000",
      "Cjsl": "500",
      "Cjje": "95000.00",
      "Sxf": "9.50",
      "Yhs": "47.50",
      "Ghf": "0.95",
      "Zjye": "10000.09",
      "Gfye": "600",
      "Market": "HA",
      "Cjbh": "73939800",
      "Wtbh": "1917840",
      "Gddm": "A664015685",
      "Dwc": "",
      "Qqhs": null,
      "Mmlb": "S",
      "Htxh": "0801917840",
      "Wtxh": "1917840",
      "Cpbm": "",
      "Cjxh": "73939800",
      "Wtsl": "500",
      "Wtjg": "190.0000",
      "Gfbcye": "600",
      "Jsxf": "4.36",
      "Qsf": "0.00",
      "Jygf": "0.00",
      "Jsf": "0.00",
      "Zgf": "0.00",
      "Qtf": "0.00",
      "Qtfy": "0.00",
      "Zjfss": "94942.05",
      "Syje": "10000.09",
      "Zqyjlx": "0.00000000",
      "Jsrq": "20260120",
      "Mmlb_ex": "S",
      "Mmlb_bs": "S"
    },
    {
      "Cjrq": "20260120",
      "Cjsj": "130433",
      "Cjsj2": "130433",
      "Zqdm": "300450",
      "Zqmc": "先导智能",
      "Mmsm": "证券买入",
      "Cjjg": "57.7122",
      "Cjsl": "1800",
      "Cjje": "103882.00",
      "Sxf": "10.39",
      "Yhs": "0.00",
      "Ghf": "0.00",
      "Zjye": "-84941.96",
      "Gfye": "3100",
      "Market": "SA",
      "Cjbh": "0104000059004026",
      "Wtbh": "1367988",
      "Gddm": "0917534836",
      "Dwc": "",
      "Qqhs": null,
      "Mmlb": "B",
      "Htxh": "0801367988",
      "Wtxh": "1367988",
      "Cpbm": "",
      "Cjxh": "0104000059004026",
      "Wtsl": "1800",
      "Wtjg": "57.7300",
      "Gfbcye": "3100",
      "Jsxf": "3.75",
      "Qsf": "0.00",
      "Jygf": "0.00",
      "Jsf": "0.00",
      "Zgf": "0.00",
      "Qtf": "0.00",
      "Qtfy": "0.00",
      "Zjfss": "-103892.39",
      "Syje": "-84941.96",
      "Zqyjlx": "0.00000000",
      "Jsrq": "20260120",
      "Mmlb_ex": "B",
      "Mmlb_bs": "B"
    },
    {
      "Cjrq": "20260120",
      "Cjsj": "130355",
      "Cjsj2": "130355",
      "Zqdm": "688525",
      "Zqmc": "佰维存储",
      "Mmsm": "证券买入",
      "Cjjg": "188.0000",
      "Cjsl": "500",
      "Cjje": "94000.00",
      "Sxf": "9.40",
      "Yhs": "0.00",
      "Ghf": "0.94",
      "Zjye": "18950.43",
      "Gfye": "1100",
      "Market": "HA",
      "Cjbh": "49773158",
      "Wtbh": "1363189",
      "Gddm": "A664015685",
      "Dwc": "",
      "Qqhs": null,
      "Mmlb": "B",
      "Htxh": "0801363189",
      "Wtxh": "1363189",
      "Cpbm": "",
      "Cjxh": "49773158",
      "Wtsl": "500",
      "Wtjg": "188.0000",
      "Gfbcye": "1100",
      "Jsxf": "4.32",
      "Qsf": "0.00",
      "Jygf": "0.00",
      "Jsf": "0.00",
      "Zgf": "0.00",
      "Qtf": "0.00",
      "Qtfy": "0.00",
      "Zjfss": "-94010.34",
      "Syje": "18950.43",
      "Zqyjlx": "0.00000000",
      "Jsrq": "20260120",
      "Mmlb_ex": "B",
      "Mmlb_bs": "B"
    },
    {
      "Cjrq": "20260120",
      "Cjsj": "130155",
      "Cjsj2": "130155",
      "Zqdm": "002657",
      "Zqmc": "中科金财",
      "Mmsm": "证券卖出",
      "Cjjg": "30.3240",
      "Cjsl": "4500",
      "Cjje": "136458.00",
      "Sxf": "13.65",
      "Yhs": "68.23",
      "Ghf": "0.00",
      "Zjye": "112960.77",
      "Gfye": "1500",
      "Market": "SA",
      "Cjbh": "0103000059073832",
      "Wtbh": "1351027",
      "Gddm": "0917534836",
      "Dwc": "",
      "Qqhs": null,
      "Mmlb": "S",
      "Htxh": "0801351027",
      "Wtxh": "1351027",
      "Cpbm": "",
      "Cjxh": "0103000059073832",
      "Wtsl": "4500",
      "Wtjg": "30.3200",
      "Gfbcye": "1500",
      "Jsxf": "4.91",
      "Qsf": "0.00",
      "Jygf": "0.00",
      "Jsf": "0.00",
      "Zgf": "0.00",
      "Qtf": "0.00",
      "Qtfy": "0.00",
      "Zjfss": "136376.12",
      "Syje": "112960.77",
      "Zqyjlx": "0.00000000",
      "Jsrq": "20260120",
      "Mmlb_ex": "S",
      "Mmlb_bs": "S"
    },
    {
      "Cjrq": "20260120",
      "Cjsj": "130001",
      "Cjsj2": "130001",
      "Zqdm": "002465",
      "Zqmc": "海格通信",
      "Mmsm": "证券卖出",
      "Cjjg": "17.6700",
      "Cjsl": "3500",
      "Cjje": "61845.00",
      "Sxf": "6.18",
      "Yhs": "30.93",
      "Ghf": "0.00",
      "Zjye": "-23415.35",
      "Gfye": "0",
      "Market": "SA",
      "Cjbh": "0105000058299393",
      "Wtbh": "1336227",
      "Gddm": "0917534836",
      "Dwc": "",
      "Qqhs": null,
      "Mmlb": "S",
      "Htxh": "0801336227",
      "Wtxh": "1336227",
      "Cpbm": "",
      "Cjxh": "0105000058299393",
      "Wtsl": "3500",
      "Wtjg": "17.6700",
      "Gfbcye": "0",
      "Jsxf": "2.21",
      "Qsf": "0.00",
      "Jygf": "0.00",
      "Jsf": "0.00",
      "Zgf": "0.00",
      "Qtf": "0.00",
      "Qtfy": "0.00",
      "Zjfss": "61807.89",
      "Syje": "-23415.35",
      "Zqyjlx": "0.00000000",
      "Jsrq": "20260120",
      "Mmlb_ex": "S",
      "Mmlb_bs": "S"
    },
    {
      "Cjrq": "20260120",
      "Cjsj": "094801",
      "Cjsj2": "094801",
      "Zqdm": "002657",
      "Zqmc": "中科金财",
      "Mmsm": "证券买入",
      "Cjjg": "30.9100",
      "Cjsl": "700",
      "Cjje": "21637.00",
      "Sxf": "5.00",
      "Yhs": "0.00",
      "Ghf": "0.00",
      "Zjye": "-85223.24",
      "Gfye": "6000",
      "Market": "SA",
      "Cjbh": "0103000017425127",
      "Wtbh": "505838",
      "Gddm": "0917534836",
      "Dwc": "",
      "Qqhs": null,
      "Mmlb": "B",
      "Htxh": "0800505838",
      "Wtxh": "505838",
      "Cpbm": "",
      "Cjxh": "0103000017425127",
      "Wtsl": "700",
      "Wtjg": "30.9100",
      "Gfbcye": "6000",
      "Jsxf": "3.61",
      "Qsf": "0.00",
      "Jygf": "0.00",
      "Jsf": "0.00",
      "Zgf": "0.00",
      "Qtf": "0.00",
      "Qtfy": "0.00",
      "Zjfss": "-21642.00",
      "Syje": "-85223.24",
      "Zqyjlx": "0.00000000",
      "Jsrq": "20260120",
      "Mmlb_ex": "B",
      "Mmlb_bs": "B"
    },
    {
      "Cjrq": "20260120",
      "Cjsj": "094635",
      "Cjsj2": "094635",
      "Zqdm": "300450",
      "Zqmc": "先导智能",
      "Mmsm": "证券买入",
      "Cjjg": "59.6000",
      "Cjsl": "300",
      "Cjje": "17880.00",
      "Sxf": "5.00",
      "Yhs": "0.00",
      "Ghf": "0.00",
      "Zjye": "-63581.24",
      "Gfye": "1300",
      "Market": "SA",
      "Cjbh": "0104000017490133",
      "Wtbh": "491351",
      "Gddm": "0917534836",
      "Dwc": "",
      "Qqhs": null,
      "Mmlb": "B",
      "Htxh": "0800491351",
      "Wtxh": "491351",
      "Cpbm": "",
      "Cjxh": "0104000017490133",
      "Wtsl": "300",
      "Wtjg": "59.6000",
      "Gfbcye": "1300",
      "Jsxf": "3.85",
      "Qsf": "0.00",
      "Jygf": "0.00",
      "Jsf": "0.00",
      "Zgf": "0.00",
      "Qtf": "0.00",
      "Qtfy": "0.00",
      "Zjfss": "-17885.00",
      "Syje": "-63581.24",
      "Zqyjlx": "0.00000000",
      "Jsrq": "20260120",
      "Mmlb_ex": "B",
      "Mmlb_bs": "B"
    },
    {
      "Cjrq": "20260120",
      "Cjsj": "100030",
      "Cjsj2": "100030",
      "Zqdm": "002657",
      "Zqmc": "中科金财",
      "Mmsm": "证券买入",
      "Cjjg": "30.8000",
      "Cjsl": "400",
      "Cjje": "12320.00",
      "Sxf": "5.00",
      "Yhs": "0.00",
      "Ghf": "0.00",
      "Zjye": "-45696.24",
      "Gfye": "5300",
      "Market": "SA",
      "Cjbh": "0103000024536261",
      "Wtbh": "412196",
      "Gddm": "0917534836",
      "Dwc": "",
      "Qqhs": null,
      "Mmlb": "B",
      "Htxh": "0800412196",
      "Wtxh": "412196",
      "Cpbm": "",
      "Cjxh": "0103000024536261",
      "Wtsl": "400",
      "Wtjg": "30.8000",
      "Gfbcye": "5300",
      "Jsxf": "4.21",
      "Qsf": "0.00",
      "Jygf": "0.00",
      "Jsf": "0.00",
      "Zgf": "0.00",
      "Qtf": "0.00",
      "Qtfy": "0.00",
      "Zjfss": "-12325.00",
      "Syje": "-45696.24",
      "Zqyjlx": "0.00000000",
      "Jsrq": "20260120",
      "Mmlb_ex": "B",
      "Mmlb_bs": "B"
    },
    {
      "Cjrq": "20260120",
      "Cjsj": "093942",
      "Cjsj2": "093942",
      "Zqdm": "300450",
      "Zqmc": "先导智能",
      "Mmsm": "证券买入",
      "Cjjg": "59.9300",
      "Cjsl": "300",
      "Cjje": "17979.00",
      "Sxf": "5.00",
      "Yhs": "0.00",
      "Ghf": "0.00",
      "Zjye": "-33371.24",
      "Gfye": "1000",
      "Market": "SA",
      "Cjbh": "0104000012072168",
      "Wtbh": "377865",
      "Gddm": "0917534836",
      "Dwc": "",
      "Qqhs": null,
      "Mmlb": "B",
      "Htxh": "0800377865",
      "Wtxh": "377865",
      "Cpbm": "",
      "Cjxh": "0104000012072168",
      "Wtsl": "300",
      "Wtjg": "59.9300",
      "Gfbcye": "1000",
      "Jsxf": "3.85",
      "Qsf": "0.00",
      "Jygf": "0.00",
      "Jsf": "0.00",
      "Zgf": "0.00",
      "Qtf": "0.00",
      "Qtfy": "0.00",
      "Zjfss": "-17984.00",
      "Syje": "-33371.24",
      "Zqyjlx": "0.00000000",
      "Jsrq": "20260120",
      "Mmlb_ex": "B",
      "Mmlb_bs": "B"
    },
    {
      "Cjrq": "20260120",
      "Cjsj": "093824",
      "Cjsj2": "093824",
      "Zqdm": "002657",
      "Zqmc": "中科金财",
      "Mmsm": "证券买入",
      "Cjjg": "30.9100",
      "Cjsl": "400",
      "Cjje": "12364.00",
      "Sxf": "5.00",
      "Yhs": "0.00",
      "Ghf": "0.00",
      "Zjye": "-15387.24",
      "Gfye": "4900",
      "Market": "SA",
      "Cjbh": "0103000010514408",
      "Wtbh": "351087",
      "Gddm": "0917534836",
      "Dwc": "",
      "Qqhs": null,
      "Mmlb": "B",
      "Htxh": "0800351087",
      "Wtxh": "351087",
      "Cpbm": "",
      "Cjxh": "0103000010514408",
      "Wtsl": "400",
      "Wtjg": "30.9100",
      "Gfbcye": "4900",
      "Jsxf": "4.21",
      "Qsf": "0.00",
      "Jygf": "0.00",
      "Jsf": "0.00",
      "Zgf": "0.00",
      "Qtf": "0.00",
      "Qtfy": "0.00",
      "Zjfss": "-12369.00",
      "Syje": "-15387.24",
      "Zqyjlx": "0.00000000",
      "Jsrq": "20260120",
      "Mmlb_ex": "B",
      "Mmlb_bs": "B"
    },
    {
      "Cjrq": "20260119",
      "Cjsj": "112001",
      "Cjsj2": "112001",
      "Zqdm": "688525",
      "Zqmc": "佰维存储",
      "Mmsm": "证券卖出",
      "Cjjg": "177.0000",
      "Cjsl": "200",
      "Cjje": "35400.00",
      "Sxf": "8.85",
      "Yhs": "17.70",
      "Ghf": "0.35",
      "Zjye": "31386.57",
      "Gfye": "600",
      "Market": "HA",
      "Cjbh": "42607057",
      "Wtbh": "1154077",
      "Gddm": "A664015685",
      "Dwc": "",
      "Qqhs": null,
      "Mmlb": "S",
      "Htxh": "0801154077",
      "Wtxh": "1154077",
      "Cpbm": "",
      "Cjxh": "42607057",
      "Wtsl": "200",
      "Wtjg": "177.0000",
      "Gfbcye": "600",
      "Jsxf": "6.93",
      "Qsf": "0.00",
      "Jygf": "0.00",
      "Jsf": "0.00",
      "Zgf": "0.00",
      "Qtf": "0.00",
      "Qtfy": "0.00",
      "Zjfss": "35373.10",
      "Syje": "31386.57",
      "Zqyjlx": "0.00000000",
      "Jsrq": "20260119",
      "Mmlb_ex": "S",
      "Mmlb_bs": "S"
    },
    {
      "Cjrq": "20260119",
      "Cjsj": "105128",
      "Cjsj2": "105128",
      "Zqdm": "688525",
      "Zqmc": "佰维存储",
      "Mmsm": "证券买入",
      "Cjjg": "174.7400",
      "Cjsl": "200",
      "Cjje": "34948.00",
      "Sxf": "8.74",
      "Yhs": "0.00",
      "Ghf": "0.35",
      "Zjye": "-3986.53",
      "Gfye": "800",
      "Market": "HA",
      "Cjbh": "37195413",
      "Wtbh": "1145349",
      "Gddm": "A664015685",
      "Dwc": "",
      "Qqhs": null,
      "Mmlb": "B",
      "Htxh": "0801145349",
      "Wtxh": "1145349",
      "Cpbm": "",
      "Cjxh": "37195413",
      "Wtsl": "200",
      "Wtjg": "174.7400",
      "Gfbcye": "800",
      "Jsxf": "6.85",
      "Qsf": "0.00",
      "Jygf": "0.00",
      "Jsf": "0.00",
      "Zgf": "0.00",
      "Qtf": "0.00",
      "Qtfy": "0.00",
      "Zjfss": "-34957.09",
      "Syje": "-3986.53",
      "Zqyjlx": "0.00000000",
      "Jsrq": "20260119",
      "Mmlb_ex": "B",
      "Mmlb_bs": "B"
    },
    {
      "Cjrq": "20260119",
      "Cjsj": "103101",
      "Cjsj2": "103101",
      "Zqdm": "300010",
      "Zqmc": "豆神教育",
      "Mmsm": "证券卖出",
      "Cjjg": "7.8800",
      "Cjsl": "9000",
      "Cjje": "70920.00",
      "Sxf": "17.73",
      "Yhs": "35.46",
      "Ghf": "0.00",
      "Zjye": "30970.56",
      "Gfye": "0",
      "Market": "SA",
      "Cjbh": "0103000039692062",
      "Wtbh": "1009655",
      "Gddm": "0917534836",
      "Dwc": "",
      "Qqhs": null,
      "Mmlb": "S",
      "Htxh": "0801009655",
      "Wtxh": "1009655",
      "Cpbm": "",
      "Cjxh": "0103000039692062",
      "Wtsl": "9000",
      "Wtjg": "7.8800",
      "Gfbcye": "0",
      "Jsxf": "13.17",
      "Qsf": "0.00",
      "Jygf": "0.00",
      "Jsf": "0.00",
      "Zgf": "0.00",
      "Qtf": "0.00",
      "Qtfy": "0.00",
      "Zjfss": "70866.81",
      "Syje": "30970.56",
      "Zqyjlx": "0.00000000",
      "Jsrq": "20260119",
      "Mmlb_ex": "S",
      "Mmlb_bs": "S"
    },
    {
      "Cjrq": "20260119",
      "Cjsj": "094009",
      "Cjsj2": "094009",
      "Zqdm": "300450",
      "Zqmc": "先导智能",
      "Mmsm": "证券买入",
      "Cjjg": "60.1500",
      "Cjsl": "700",
      "Cjje": "42105.00",
      "Sxf": "10.53",
      "Yhs": "0.00",
      "Ghf": "0.00",
      "Zjye": "-39896.25",
      "Gfye": "700",
      "Market": "SA",
      "Cjbh": "0104000012763861",
      "Wtbh": "410409",
      "Gddm": "0917534836",
      "Dwc": "",
      "Qqhs": null,
      "Mmlb": "B",
      "Htxh": "0800410409",
      "Wtxh": "410409",
      "Cpbm": "",
      "Cjxh": "0104000012763861",
      "Wtsl": "700",
      "Wtjg": "60.1800",
      "Gfbcye": "700",
      "Jsxf": "7.83",
      "Qsf": "0.00",
      "Jygf": "0.00",
      "Jsf": "0.00",
      "Zgf": "0.00",
      "Qtf": "0.00",
      "Qtfy": "0.00",
      "Zjfss": "-42115.53",
      "Syje": "-39896.25",
      "Zqyjlx": "0.00000000",
      "Jsrq": "20260119",
      "Mmlb_ex": "B",
      "Mmlb_bs": "B"
    },
    {
      "Cjrq": "20260119",
      "Cjsj": "141035",
      "Cjsj2": "141035",
      "Zqdm": "603920",
      "Zqmc": "世运电路",
      "Mmsm": "证券买入",
      "Cjjg": "58.5800",
      "Cjsl": "200",
      "Cjje": "11716.00",
      "Sxf": "5.00",
      "Yhs": "0.00",
      "Ghf": "0.12",
      "Zjye": "2219.28",
      "Gfye": "1000",
      "Market": "HA",
      "Cjbh": "59838013",
      "Wtbh": "367276",
      "Gddm": "A664015685",
      "Dwc": "",
      "Qqhs": null,
      "Mmlb": "B",
      "Htxh": "0800367276",
      "Wtxh": "367276",
      "Cpbm": "",
      "Cjxh": "59838013",
      "Wtsl": "200",
      "Wtjg": "58.5800",
      "Gfbcye": "1000",
      "Jsxf": "4.36",
      "Qsf": "0.00",
      "Jygf": "0.00",
      "Jsf": "0.00",
      "Zgf": "0.00",
      "Qtf": "0.00",
      "Qtfy": "0.00",
      "Zjfss": "-11721.12",
      "Syje": "2219.28",
      "Zqyjlx": "0.00000000",
      "Jsrq": "20260119",
      "Mmlb_ex": "B",
      "Mmlb_bs": "B"
    },
    {
      "Cjrq": "20260119",
      "Cjsj": "093422",
      "Cjsj2": "093422",
      "Zqdm": "603920",
      "Zqmc": "世运电路",
      "Mmsm": "证券买入",
      "Cjjg": "59.0100",
      "Cjsl": "400",
      "Cjje": "23604.00",
      "Sxf": "5.90",
      "Yhs": "0.00",
      "Ghf": "0.24",
      "Zjye": "13940.40",
      "Gfye": "800",
      "Market": "HA",
      "Cjbh": "5959705",
      "Wtbh": "288368",
      "Gddm": "A664015685",
      "Dwc": "",
      "Qqhs": null,
      "Mmlb": "B",
      "Htxh": "0800288368",
      "Wtxh": "288368",
      "Cpbm": "",
      "Cjxh": "5959705",
      "Wtsl": "400",
      "Wtjg": "59.0100",
      "Gfbcye": "800",
      "Jsxf": "4.63",
      "Qsf": "0.00",
      "Jygf": "0.00",
      "Jsf": "0.00",
      "Zgf": "0.00",
      "Qtf": "0.00",
      "Qtfy": "0.00",
      "Zjfss": "-23610.14",
      "Syje": "13940.40",
      "Zqyjlx": "0.00000000",
      "Jsrq": "20260119",
      "Mmlb_ex": "B",
      "Mmlb_bs": "B"
    },
    {
      "Cjrq": "20260119",
      "Cjsj": "093213",
      "Cjsj2": "093213",
      "Zqdm": "603920",
      "Zqmc": "世运电路",
      "Mmsm": "证券买入",
      "Cjjg": "58.9300",
      "Cjsl": "200",
      "Cjje": "11786.00",
      "Sxf": "5.00",
      "Yhs": "0.00",
      "Ghf": "0.12",
      "Zjye": "37550.54",
      "Gfye": "400",
      "Market": "HA",
      "Cjbh": "3811439",
      "Wtbh": "230878",
      "Gddm": "A664015685",
      "Dwc": "",
      "Qqhs": null,
      "Mmlb": "B",
      "Htxh": "0800230878",
      "Wtxh": "230878",
      "Cpbm": "",
      "Cjxh": "3811439",
      "Wtsl": "200",
      "Wtjg": "58.9500",
      "Gfbcye": "400",
      "Jsxf": "4.36",
      "Qsf": "0.00",
      "Jygf": "0.00",
      "Jsf": "0.00",
      "Zgf": "0.00",
      "Qtf": "0.00",
      "Qtfy": "0.00",
      "Zjfss": "-11791.12",
      "Syje": "37550.54",
      "Zqyjlx": "0.00000000",
      "Jsrq": "20260119",
      "Mmlb_ex": "B",
      "Mmlb_bs": "B"
    },
    {
      "Cjrq": "20260119",
      "Cjsj": "093020",
      "Cjsj2": "093020",
      "Zqdm": "603881",
      "Zqmc": "数据港",
      "Mmsm": "证券卖出",
      "Cjjg": "34.6800",
      "Cjsl": "2500",
      "Cjje": "86700.00",
      "Sxf": "21.68",
      "Yhs": "43.35",
      "Ghf": "0.85",
      "Zjye": "49341.66",
      "Gfye": "0",
      "Market": "HA",
      "Cjbh": "1019489",
      "Wtbh": "158720",
      "Gddm": "A664015685",
      "Dwc": "",
      "Qqhs": null,
      "Mmlb": "S",
      "Htxh": "0800158720",
      "Wtxh": "158720",
      "Cpbm": "",
      "Cjxh": "1019489",
      "Wtsl": "2500",
      "Wtjg": "34.5100",
      "Gfbcye": "0",
      "Jsxf": "16.99",
      "Qsf": "0.00",
      "Jygf": "0.00",
      "Jsf": "0.00",
      "Zgf": "0.00",
      "Qtf": "0.00",
      "Qtfy": "0.00",
      "Zjfss": "86634.12",
      "Syje": "49341.66",
      "Zqyjlx": "0.00000000",
      "Jsrq": "20260119",
      "Mmlb_ex": "S",
      "Mmlb_bs": "S"
    },
    {
      "Cjrq": "20260119",
      "Cjsj": "093012",
      "Cjsj2": "093012",
      "Zqdm": "603920",
      "Zqmc": "世运电路",
      "Mmsm": "证券买入",
      "Cjjg": "58.4000",
      "Cjsl": "200",
      "Cjje": "11680.00",
      "Sxf": "5.00",
      "Yhs": "0.00",
      "Ghf": "0.12",
      "Zjye": "-37292.46",
      "Gfye": "200",
      "Market": "HA",
      "Cjbh": "817983",
      "Wtbh": "138825",
      "Gddm": "A664015685",
      "Dwc": "",
      "Qqhs": null,
      "Mmlb": "B",
      "Htxh": "0800138825",
      "Wtxh": "138825",
      "Cpbm": "",
      "Cjxh": "817983",
      "Wtsl": "200",
      "Wtjg": "58.5100",
      "Gfbcye": "200",
      "Jsxf": "4.37",
      "Qsf": "0.00",
      "Jygf": "0.00",
      "Jsf": "0.00",
      "Zgf": "0.00",
      "Qtf": "0.00",
      "Qtfy": "0.00",
      "Zjfss": "-11685.12",
      "Syje": "-37292.46",
      "Zqyjlx": "0.00000000",
      "Jsrq": "20260119",
      "Mmlb_ex": "B",
      "Mmlb_bs": "B"
    },
    {
      "Cjrq": "20260116",
      "Cjsj": "103858",
      "Cjsj2": "103858",
      "Zqdm": "688525",
      "Zqmc": "佰维存储",
      "Mmsm": "证券买入",
      "Cjjg": "177.1000",
      "Cjsl": "600",
      "Cjje": "106260.00",
      "Sxf": "26.57",
      "Yhs": "0.00",
      "Ghf": "1.06",
      "Zjye": "65452.70",
      "Gfye": "600",
      "Market": "HA",
      "Cjbh": "36620109",
      "Wtbh": "1111652",
      "Gddm": "A664015685",
      "Dwc": "",
      "Qqhs": null,
      "Mmlb": "B",
      "Htxh": "0801111652",
      "Wtxh": "1111652",
      "Cpbm": "",
      "Cjxh": "36620109",
      "Wtsl": "600",
      "Wtjg": "177.1000",
      "Gfbcye": "600",
      "Jsxf": "20.82",
      "Qsf": "0.00",
      "Jygf": "0.00",
      "Jsf": "0.00",
      "Zgf": "0.00",
      "Qtf": "0.00",
      "Qtfy": "0.00",
      "Zjfss": "-106287.63",
      "Syje": "65452.70",
      "Zqyjlx": "0.00000000",
      "Jsrq": "20260116",
      "Mmlb_ex": "B",
      "Mmlb_bs": "B"
    },
    {
      "Cjrq": "20260116",
      "Cjsj": "102459",
      "Cjsj2": "102459",
      "Zqdm": "920021",
      "Zqmc": "流金科技",
      "Mmsm": "证券卖出",
      "Cjjg": "9.8000",
      "Cjsl": "3205",
      "Cjje": "31409.00",
      "Sxf": "21.99",
      "Yhs": "15.70",
      "Ghf": "0.00",
      "Zjye": "171740.33",
      "Gfye": "0",
      "Market": "B",
      "Cjbh": "01102830",
      "Wtbh": "996972",
      "Gddm": "0917534836",
      "Dwc": "",
      "Qqhs": null,
      "Mmlb": "S",
      "Htxh": "B2500128",
      "Wtxh": "996972",
      "Cpbm": "",
      "Cjxh": "01102830",
      "Wtsl": "3205",
      "Wtjg": "9.8000",
      "Gfbcye": "0",
      "Jsxf": "17.75",
      "Qsf": "0.00",
      "Jygf": "0.00",
      "Jsf": "0.00",
      "Zgf": "0.00",
      "Qtf": "0.00",
      "Qtfy": "0.00",
      "Zjfss": "31371.31",
      "Syje": "171740.33",
      "Zqyjlx": "0.00000000",
      "Jsrq": "20260116",
      "Mmlb_ex": "S",
      "Mmlb_bs": "S"
    },
    {
      "Cjrq": "20260116",
      "Cjsj": "102326",
      "Cjsj2": "102326",
      "Zqdm": "002044",
      "Zqmc": "美年健康",
      "Mmsm": "证券卖出",
      "Cjjg": "7.6700",
      "Cjsl": "9200",
      "Cjje": "70564.00",
      "Sxf": "17.64",
      "Yhs": "35.28",
      "Ghf": "0.00",
      "Zjye": "140369.02",
      "Gfye": "0",
      "Market": "SA",
      "Cjbh": "0104000038132314",
      "Wtbh": "982587",
      "Gddm": "0917534836",
      "Dwc": "",
      "Qqhs": null,
      "Mmlb": "S",
      "Htxh": "0800982587",
      "Wtxh": "982587",
      "Cpbm": "",
      "Cjxh": "0104000038132314",
      "Wtsl": "9200",
      "Wtjg": "7.6700",
      "Gfbcye": "0",
      "Jsxf": "13.12",
      "Qsf": "0.00",
      "Jygf": "0.00",
      "Jsf": "0.00",
      "Zgf": "0.00",
      "Qtf": "0.00",
      "Qtfy": "0.00",
      "Zjfss": "70511.08",
      "Syje": "140369.02",
      "Zqyjlx": "0.00000000",
      "Jsrq": "20260116",
      "Mmlb_ex": "S",
      "Mmlb_bs": "S"
    },
    {
      "Cjrq": "20260115",
      "Cjsj": "145046",
      "Cjsj2": "145046",
      "Zqdm": "002044",
      "Zqmc": "美年健康",
      "Mmsm": "证券买入",
      "Cjjg": "8.5700",
      "Cjsl": "9200",
      "Cjje": "78844.00",
      "Sxf": "19.71",
      "Yhs": "0.00",
      "Ghf": "0.00",
      "Zjye": "56522.22",
      "Gfye": "9200",
      "Market": "SA",
      "Cjbh": "0102000093396329",
      "Wtbh": "2021798",
      "Gddm": "0917534836",
      "Dwc": "",
      "Qqhs": null,
      "Mmlb": "B",
      "Htxh": "0802021798",
      "Wtxh": "2021798",
      "Cpbm": "",
      "Cjxh": "0102000093396329",
      "Wtsl": "9200",
      "Wtjg": "8.5700",
      "Gfbcye": "9200",
      "Jsxf": "14.65",
      "Qsf": "0.00",
      "Jygf": "0.00",
      "Jsf": "0.00",
      "Zgf": "0.00",
      "Qtf": "0.00",
      "Qtfy": "0.00",
      "Zjfss": "-78863.71",
      "Syje": "56522.22",
      "Zqyjlx": "0.00000000",
      "Jsrq": "20260115",
      "Mmlb_ex": "B",
      "Mmlb_bs": "B"
    },
    {
      "Cjrq": "20260115",
      "Cjsj": "141045",
      "Cjsj2": "141045",
      "Zqdm": "600435",
      "Zqmc": "北方导航",
      "Mmsm": "证券卖出",
      "Cjjg": "17.8100",
      "Cjsl": "4200",
      "Cjje": "74802.00",
      "Sxf": "18.70",
      "Yhs": "37.40",
      "Ghf": "0.75",
      "Zjye": "135385.93",
      "Gfye": "0",
      "Market": "HA",
      "Cjbh": "59888990",
      "Wtbh": "1792097",
      "Gddm": "A664015685",
      "Dwc": "",
      "Qqhs": null,
      "Mmlb": "S",
      "Htxh": "0801792097",
      "Wtxh": "1792097",
      "Cpbm": "",
      "Cjxh": "59888990",
      "Wtsl": "4200",
      "Wtjg": "17.8100",
      "Gfbcye": "0",
      "Jsxf": "14.65",
      "Qsf": "0.00",
      "Jygf": "0.00",
      "Jsf": "0.00",
      "Zgf": "0.00",
      "Qtf": "0.00",
      "Qtfy": "0.00",
      "Zjfss": "74745.15",
      "Syje": "135385.93",
      "Zqyjlx": "0.00000000",
      "Jsrq": "20260115",
      "Mmlb_ex": "S",
      "Mmlb_bs": "S"
    },
    {
      "Cjrq": "20260115",
      "Cjsj": "133246",
      "Cjsj2": "133246",
      "Zqdm": "920021",
      "Zqmc": "流金科技",
      "Mmsm": "证券卖出",
      "Cjjg": "11.6373",
      "Cjsl": "3529",
      "Cjje": "41068.03",
      "Sxf": "28.75",
      "Yhs": "20.53",
      "Ghf": "0.00",
      "Zjye": "60640.78",
      "Gfye": "3205",
      "Market": "B",
      "Cjbh": "01963022",
      "Wtbh": "1620372",
      "Gddm": "0917534836",
      "Dwc": "",
      "Qqhs": null,
      "Mmlb": "S",
      "Htxh": "B2500102",
      "Wtxh": "1620372",
      "Cpbm": "",
      "Cjxh": "01963022",
      "Wtsl": "3529",
      "Wtjg": "11.6300",
      "Gfbcye": "3205",
      "Jsxf": "23.20",
      "Qsf": "0.00",
      "Jygf": "0.00",
      "Jsf": "0.00",
      "Zgf": "0.00",
      "Qtf": "0.00",
      "Qtfy": "0.00",
      "Zjfss": "41018.75",
      "Syje": "60640.78",
      "Zqyjlx": "0.00000000",
      "Jsrq": "20260115",
      "Mmlb_ex": "S",
      "Mmlb_bs": "S"
    },
    {
      "Cjrq": "20260115",
      "Cjsj": "133055",
      "Cjsj2": "133055",
      "Zqdm": "920021",
      "Zqmc": "流金科技",
      "Mmsm": "证券卖出",
      "Cjjg": "11.6000",
      "Cjsl": "3500",
      "Cjje": "40600.00",
      "Sxf": "28.42",
      "Yhs": "20.30",
      "Ghf": "0.00",
      "Zjye": "19622.03",
      "Gfye": "6734",
      "Market": "B",
      "Cjbh": "01951101",
      "Wtbh": "1611456",
      "Gddm": "0917534836",
      "Dwc": "",
      "Qqhs": null,
      "Mmlb": "S",
      "Htxh": "B2500100",
      "Wtxh": "1611456",
      "Cpbm": "",
      "Cjxh": "01951101",
      "Wtsl": "3500",
      "Wtjg": "11.5800",
      "Gfbcye": "6734",
      "Jsxf": "22.93",
      "Qsf": "0.00",
      "Jygf": "0.00",
      "Jsf": "0.00",
      "Zgf": "0.00",
      "Qtf": "0.00",
      "Qtfy": "0.00",
      "Zjfss": "40551.28",
      "Syje": "19622.03",
      "Zqyjlx": "0.00000000",
      "Jsrq": "20260115",
      "Mmlb_ex": "S",
      "Mmlb_bs": "S"
    },
    {
      "Cjrq": "20260115",
      "Cjsj": "131157",
      "Cjsj2": "131157",
      "Zqdm": "603881",
      "Zqmc": "数据港",
      "Mmsm": "证券买入",
      "Cjjg": "40.0957",
      "Cjsl": "700",
      "Cjje": "28066.98",
      "Sxf": "7.02",
      "Yhs": "0.00",
      "Ghf": "0.28",
      "Zjye": "-20929.25",
      "Gfye": "2500",
      "Market": "HA",
      "Cjbh": "48162096",
      "Wtbh": "1506152",
      "Gddm": "A664015685",
      "Dwc": "",
      "Qqhs": null,
      "Mmlb": "B",
      "Htxh": "0801506152",
      "Wtxh": "1506152",
      "Cpbm": "",
      "Cjxh": "48162096",
      "Wtsl": "700",
      "Wtjg": "40.2800",
      "Gfbcye": "2500",
      "Jsxf": "5.51",
      "Qsf": "0.00",
      "Jygf": "0.00",
      "Jsf": "0.00",
      "Zgf": "0.00",
      "Qtf": "0.00",
      "Qtfy": "0.00",
      "Zjfss": "-28074.28",
      "Syje": "-20929.25",
      "Zqyjlx": "0.00000000",
      "Jsrq": "20260115",
      "Mmlb_ex": "B",
      "Mmlb_bs": "B"
    },
    {
      "Cjrq": "20260115",
      "Cjsj": "112939",
      "Cjsj2": "112939",
      "Zqdm": "002657",
      "Zqmc": "中科金财",
      "Mmsm": "证券买入",
      "Cjjg": "33.5200",
      "Cjsl": "700",
      "Cjje": "23464.00",
      "Sxf": "5.87",
      "Yhs": "0.00",
      "Ghf": "0.00",
      "Zjye": "7145.03",
      "Gfye": "4500",
      "Market": "SA",
      "Cjbh": "0105000059112462",
      "Wtbh": "1387502",
      "Gddm": "0917534836",
      "Dwc": "",
      "Qqhs": null,
      "Mmlb": "B",
      "Htxh": "0801387502",
      "Wtxh": "1387502",
      "Cpbm": "",
      "Cjxh": "0105000059112462",
      "Wtsl": "700",
      "Wtjg": "33.5200",
      "Gfbcye": "4500",
      "Jsxf": "4.37",
      "Qsf": "0.00",
      "Jygf": "0.00",
      "Jsf": "0.00",
      "Zgf": "0.00",
      "Qtf": "0.00",
      "Qtfy": "0.00",
      "Zjfss": "-23469.87",
      "Syje": "7145.03",
      "Zqyjlx": "0.00000000",
      "Jsrq": "20260115",
      "Mmlb_ex": "B",
      "Mmlb_bs": "B"
    },
    {
      "Cjrq": "20260115",
      "Cjsj": "112431",
      "Cjsj2": "112431",
      "Zqdm": "603881",
      "Zqmc": "数据港",
      "Mmsm": "证券买入",
      "Cjjg": "37.5900",
      "Cjsl": "600",
      "Cjje": "22554.00",
      "Sxf": "5.64",
      "Yhs": "0.00",
      "Ghf": "0.23",
      "Zjye": "30614.90",
      "Gfye": "1800",
      "Market": "HA",
      "Cjbh": "43653272",
      "Wtbh": "1359865",
      "Gddm": "A664015685",
      "Dwc": "",
      "Qqhs": null,
      "Mmlb": "B",
      "Htxh": "0801359865",
      "Wtxh": "1359865",
      "Cpbm": "",
      "Cjxh": "43653272",
      "Wtsl": "600",
      "Wtjg": "37.6100",
      "Gfbcye": "1800",
      "Jsxf": "4.41",
      "Qsf": "0.00",
      "Jygf": "0.00",
      "Jsf": "0.00",
      "Zgf": "0.00",
      "Qtf": "0.00",
      "Qtfy": "0.00",
      "Zjfss": "-22559.87",
      "Syje": "30614.90",
      "Zqyjlx": "0.00000000",
      "Jsrq": "20260115",
      "Mmlb_ex": "B",
      "Mmlb_bs": "B"
    },
    {
      "Cjrq": "20260115",
      "Cjsj": "112343",
      "Cjsj2": "112343",
      "Zqdm": "002657",
      "Zqmc": "中科金财",
      "Mmsm": "证券买入",
      "Cjjg": "33.7000",
      "Cjsl": "2200",
      "Cjje": "74140.00",
      "Sxf": "18.54",
      "Yhs": "0.00",
      "Ghf": "0.00",
      "Zjye": "53174.77",
      "Gfye": "3800",
      "Market": "SA",
      "Cjbh": "0105000057525285",
      "Wtbh": "1356075",
      "Gddm": "0917534836",
      "Dwc": "",
      "Qqhs": null,
      "Mmlb": "B",
      "Htxh": "0801356075",
      "Wtxh": "1356075",
      "Cpbm": "",
      "Cjxh": "0105000057525285",
      "Wtsl": "2200",
      "Wtjg": "33.7000",
      "Gfbcye": "3800",
      "Jsxf": "13.80",
      "Qsf": "0.00",
      "Jygf": "0.00",
      "Jsf": "0.00",
      "Zgf": "0.00",
      "Qtf": "0.00",
      "Qtfy": "0.00",
      "Zjfss": "-74158.54",
      "Syje": "53174.77",
      "Zqyjlx": "0.00000000",
      "Jsrq": "20260115",
      "Mmlb_ex": "B",
      "Mmlb_bs": "B"
    },
    {
      "Cjrq": "20260115",
      "Cjsj": "112334",
      "Cjsj2": "112334",
      "Zqdm": "002512",
      "Zqmc": "达华智能",
      "Mmsm": "证券卖出",
      "Cjjg": "7.0000",
      "Cjsl": "12600",
      "Cjje": "88200.00",
      "Sxf": "22.05",
      "Yhs": "44.10",
      "Ghf": "0.00",
      "Zjye": "127333.31",
      "Gfye": "0",
      "Market": "SA",
      "Cjbh": "0102000059615802",
      "Wtbh": "1355347",
      "Gddm": "0917534836",
      "Dwc": "",
      "Qqhs": null,
      "Mmlb": "S",
      "Htxh": "0801355347",
      "Wtxh": "1355347",
      "Cpbm": "",
      "Cjxh": "0102000059615802",
      "Wtsl": "12600",
      "Wtjg": "7.0000",
      "Gfbcye": "0",
      "Jsxf": "16.41",
      "Qsf": "0.00",
      "Jygf": "0.00",
      "Jsf": "0.00",
      "Zgf": "0.00",
      "Qtf": "0.00",
      "Qtfy": "0.00",
      "Zjfss": "88133.85",
      "Syje": "127333.31",
      "Zqyjlx": "0.00000000",
      "Jsrq": "20260115",
      "Mmlb_ex": "S",
      "Mmlb_bs": "S"
    },
    {
      "Cjrq": "20260115",
      "Cjsj": "112324",
      "Cjsj2": "112324",
      "Zqdm": "300102",
      "Zqmc": "乾照光电",
      "Mmsm": "证券卖出",
      "Cjjg": "32.5300",
      "Cjsl": "1900",
      "Cjje": "61807.00",
      "Sxf": "15.45",
      "Yhs": "30.90",
      "Ghf": "0.00",
      "Zjye": "39199.46",
      "Gfye": "0",
      "Market": "SA",
      "Cjbh": "0105000057452028",
      "Wtbh": "1354564",
      "Gddm": "0917534836",
      "Dwc": "",
      "Qqhs": null,
      "Mmlb": "S",
      "Htxh": "0801354564",
      "Wtxh": "1354564",
      "Cpbm": "",
      "Cjxh": "0105000057452028",
      "Wtsl": "1900",
      "Wtjg": "32.5300",
      "Gfbcye": "0",
      "Jsxf": "11.48",
      "Qsf": "0.00",
      "Jygf": "0.00",
      "Jsf": "0.00",
      "Zgf": "0.00",
      "Qtf": "0.00",
      "Qtfy": "0.00",
      "Zjfss": "61760.65",
      "Syje": "39199.46",
      "Zqyjlx": "0.00000000",
      "Jsrq": "20260115",
      "Mmlb_ex": "S",
      "Mmlb_bs": "S"
    },
    {
      "Cjrq": "20260115",
      "Cjsj": "094333",
      "Cjsj2": "094333",
      "Zqdm": "920021",
      "Zqmc": "流金科技",
      "Mmsm": "证券买入",
      "Cjjg": "13.2500",
      "Cjsl": "3205",
      "Cjje": "42466.25",
      "Sxf": "29.73",
      "Yhs": "0.00",
      "Ghf": "0.00",
      "Zjye": "-22561.19",
      "Gfye": "10234",
      "Market": "B",
      "Cjbh": "00509812",
      "Wtbh": "540277",
      "Gddm": "0917534836",
      "Dwc": "",
      "Qqhs": null,
      "Mmlb": "B",
      "Htxh": "B2500046",
      "Wtxh": "540277",
      "Cpbm": "",
      "Cjxh": "00509812",
      "Wtsl": "3205",
      "Wtjg": "13.2800",
      "Gfbcye": "10234",
      "Jsxf": "24.00",
      "Qsf": "0.00",
      "Jygf": "0.00",
      "Jsf": "0.00",
      "Zgf": "0.00",
      "Qtf": "0.00",
      "Qtfy": "0.00",
      "Zjfss": "-42495.98",
      "Syje": "-22561.19",
      "Zqyjlx": "0.00000000",
      "Jsrq": "20260115",
      "Mmlb_ex": "B",
      "Mmlb_bs": "B"
    },
    {
      "Cjrq": "20260115",
      "Cjsj": "094120",
      "Cjsj2": "094120",
      "Zqdm": "588790",
      "Zqmc": "科创智能",
      "Mmsm": "证券卖出",
      "Cjjg": "0.9160",
      "Cjsl": "39000",
      "Cjje": "35724.00",
      "Sxf": "1.79",
      "Yhs": "0.00",
      "Ghf": "0.00",
      "Zjye": "19934.79",
      "Gfye": "0",
      "Market": "HA",
      "Cjbh": "11920991",
      "Wtbh": "499358",
      "Gddm": "A664015685",
      "Dwc": "",
      "Qqhs": null,
      "Mmlb": "S",
      "Htxh": "0800499358",
      "Wtxh": "499358",
      "Cpbm": "",
      "Cjxh": "11920991",
      "Wtsl": "39000",
      "Wtjg": "0.9160",
      "Gfbcye": "0",
      "Jsxf": "0.36",
      "Qsf": "0.00",
      "Jygf": "0.00",
      "Jsf": "0.00",
      "Zgf": "0.00",
      "Qtf": "0.00",
      "Qtfy": "0.00",
      "Zjfss": "35722.21",
      "Syje": "19934.79",
      "Zqyjlx": "0.00000000",
      "Jsrq": "20260115",
      "Mmlb_ex": "S",
      "Mmlb_bs": "S"
    },
    {
      "Cjrq": "20260115",
      "Cjsj": "094054",
      "Cjsj2": "094054",
      "Zqdm": "002657",
      "Zqmc": "中科金财",
      "Mmsm": "证券买入",
      "Cjjg": "31.7900",
      "Cjsl": "1600",
      "Cjje": "50864.00",
      "Sxf": "12.72",
      "Yhs": "0.00",
      "Ghf": "0.00",
      "Zjye": "-15787.42",
      "Gfye": "1600",
      "Market": "SA",
      "Cjbh": "0105000015851457",
      "Wtbh": "490831",
      "Gddm": "0917534836",
      "Dwc": "",
      "Qqhs": null,
      "Mmlb": "B",
      "Htxh": "0800490831",
      "Wtxh": "490831",
      "Cpbm": "",
      "Cjxh": "0105000015851457",
      "Wtsl": "1600",
      "Wtjg": "31.8000",
      "Gfbcye": "1600",
      "Jsxf": "9.45",
      "Qsf": "0.00",
      "Jygf": "0.00",
      "Jsf": "0.00",
      "Zgf": "0.00",
      "Qtf": "0.00",
      "Qtfy": "0.00",
      "Zjfss": "-50876.72",
      "Syje": "-15787.42",
      "Zqyjlx": "0.00000000",
      "Jsrq": "20260115",
      "Mmlb_ex": "B",
      "Mmlb_bs": "B"
    },
    {
      "Cjrq": "20260115",
      "Cjsj": "094021",
      "Cjsj2": "094021",
      "Zqdm": "603881",
      "Zqmc": "数据港",
      "Mmsm": "证券买入",
      "Cjjg": "39.2500",
      "Cjsl": "1200",
      "Cjje": "47100.00",
      "Sxf": "11.78",
      "Yhs": "0.00",
      "Ghf": "0.47",
      "Zjye": "35089.30",
      "Gfye": "1200",
      "Market": "HA",
      "Cjbh": "11117432",
      "Wtbh": "479590",
      "Gddm": "A664015685",
      "Dwc": "",
      "Qqhs": null,
      "Mmlb": "B",
      "Htxh": "0800479590",
      "Wtxh": "479590",
      "Cpbm": "",
      "Cjxh": "11117432",
      "Wtsl": "1200",
      "Wtjg": "39.3000",
      "Gfbcye": "1200",
      "Jsxf": "9.23",
      "Qsf": "0.00",
      "Jygf": "0.00",
      "Jsf": "0.00",
      "Zgf": "0.00",
      "Qtf": "0.00",
      "Qtfy": "0.00",
      "Zjfss": "-47112.25",
      "Syje": "35089.30",
      "Zqyjlx": "0.00000000",
      "Jsrq": "20260115",
      "Mmlb_ex": "B",
      "Mmlb_bs": "B"
    },
    {
      "Cjrq": "20260115",
      "Cjsj": "093840",
      "Cjsj2": "093840",
      "Zqdm": "600879",
      "Zqmc": "航天电子",
      "Mmsm": "证券卖出",
      "Cjjg": "26.9000",
      "Cjsl": "3900",
      "Cjje": "104910.00",
      "Sxf": "26.23",
      "Yhs": "52.46",
      "Ghf": "1.06",
      "Zjye": "82201.55",
      "Gfye": "0",
      "Market": "HA",
      "Cjbh": "9797853",
      "Wtbh": "441790",
      "Gddm": "A664015685",
      "Dwc": "",
      "Qqhs": null,
      "Mmlb": "S",
      "Htxh": "0800441790",
      "Wtxh": "441790",
      "Cpbm": "",
      "Cjxh": "9797853",
      "Wtsl": "3900",
      "Wtjg": "26.9000",
      "Gfbcye": "0",
      "Jsxf": "20.56",
      "Qsf": "0.00",
      "Jygf": "0.00",
      "Jsf": "0.00",
      "Zgf": "0.00",
      "Qtf": "0.00",
      "Qtfy": "0.00",
      "Zjfss": "104830.25",
      "Syje": "82201.55",
      "Zqyjlx": "0.00000000",
      "Jsrq": "20260115",
      "Mmlb_ex": "S",
      "Mmlb_bs": "S"
    },
    {
      "Cjrq": "20260115",
      "Cjsj": "150000",
      "Cjsj2": "150000",
      "Zqdm": "920076",
      "Zqmc": "国亮新材",
      "Mmsm": "公开发行申购",
      "Cjjg": "10.7600",
      "Cjsl": "100",
      "Cjje": "1076.00",
      "Sxf": "0.00",
      "Yhs": "0.00",
      "Ghf": "0.00",
      "Zjye": "-22628.70",
      "Gfye": "0",
      "Market": "B",
      "Cjbh": "",
      "Wtbh": "0",
      "Gddm": "0917534836",
      "Dwc": "",
      "Qqhs": null,
      "Mmlb": "8B",
      "Htxh": "B2500027",
      "Wtxh": "0",
      "Cpbm": "",
      "Cjxh": "",
      "Wtsl": "100",
      "Wtjg": "10.7600",
      "Gfbcye": "0",
      "Jsxf": "0.00",
      "Qsf": "0.00",
      "Jygf": "0.00",
      "Jsf": "0.00",
      "Zgf": "0.00",
      "Qtf": "0.00",
      "Qtfy": "0.00",
      "Zjfss": "1076.00",
      "Syje": "-22628.70",
      "Zqyjlx": "0.00000000",
      "Jsrq": "20260115",
      "Mmlb_ex": "8B",
      "Mmlb_bs": "B"
    },
    {
      "Cjrq": "20260114",
      "Cjsj": "134303",
      "Cjsj2": "134303",
      "Zqdm": "588790",
      "Zqmc": "科创智能",
      "Mmsm": "证券买入",
      "Cjjg": "0.9330",
      "Cjsl": "39000",
      "Cjje": "36387.00",
      "Sxf": "1.82",
      "Yhs": "0.00",
      "Ghf": "0.00",
      "Zjye": "46786.11",
      "Gfye": "39000",
      "Market": "HA",
      "Cjbh": "69658977",
      "Wtbh": "2070358",
      "Gddm": "A664015685",
      "Dwc": "",
      "Qqhs": null,
      "Mmlb": "B",
      "Htxh": "0802070358",
      "Wtxh": "2070358",
      "Cpbm": "",
      "Cjxh": "69658977",
      "Wtsl": "39000",
      "Wtjg": "0.9330",
      "Gfbcye": "39000",
      "Jsxf": "0.36",
      "Qsf": "0.00",
      "Jygf": "0.00",
      "Jsf": "0.00",
      "Zgf": "0.00",
      "Qtf": "0.00",
      "Qtfy": "0.00",
      "Zjfss": "-36388.82",
      "Syje": "46786.11",
      "Zqyjlx": "0.00000000",
      "Jsrq": "20260114",
      "Mmlb_ex": "B",
      "Mmlb_bs": "B"
    },
    {
      "Cjrq": "20260114",
      "Cjsj": "132220",
      "Cjsj2": "132220",
      "Zqdm": "600118",
      "Zqmc": "中国卫星",
      "Mmsm": "证券卖出",
      "Cjjg": "119.3700",
      "Cjsl": "300",
      "Cjje": "35811.00",
      "Sxf": "8.95",
      "Yhs": "17.91",
      "Ghf": "0.36",
      "Zjye": "83174.93",
      "Gfye": "0",
      "Market": "HA",
      "Cjbh": "63138616",
      "Wtbh": "1904601",
      "Gddm": "A664015685",
      "Dwc": "",
      "Qqhs": null,
      "Mmlb": "S",
      "Htxh": "0801904601",
      "Wtxh": "1904601",
      "Cpbm": "",
      "Cjxh": "63138616",
      "Wtsl": "300",
      "Wtjg": "119.3700",
      "Gfbcye": "0",
      "Jsxf": "7.01",
      "Qsf": "0.00",
      "Jygf": "0.00",
      "Jsf": "0.00",
      "Zgf": "0.00",
      "Qtf": "0.00",
      "Qtfy": "0.00",
      "Zjfss": "35783.78",
      "Syje": "83174.93",
      "Zqyjlx": "0.00000000",
      "Jsrq": "20260114",
      "Mmlb_ex": "S",
      "Mmlb_bs": "S"
    },
    {
      "Cjrq": "20260114",
      "Cjsj": "130936",
      "Cjsj2": "130936",
      "Zqdm": "920021",
      "Zqmc": "流金科技",
      "Mmsm": "证券买入",
      "Cjjg": "13.1800",
      "Cjsl": "2172",
      "Cjje": "28626.96",
      "Sxf": "20.04",
      "Yhs": "0.00",
      "Ghf": "0.00",
      "Zjye": "47391.15",
      "Gfye": "7029",
      "Market": "B",
      "Cjbh": "02640799",
      "Wtbh": "1718862",
      "Gddm": "0917534836",
      "Dwc": "",
      "Qqhs": null,
      "Mmlb": "B",
      "Htxh": "B2500277",
      "Wtxh": "1718862",
      "Cpbm": "",
      "Cjxh": "02640799",
      "Wtsl": "2172",
      "Wtjg": "13.1800",
      "Gfbcye": "7029",
      "Jsxf": "16.17",
      "Qsf": "0.00",
      "Jygf": "0.00",
      "Jsf": "0.00",
      "Zgf": "0.00",
      "Qtf": "0.00",
      "Qtfy": "0.00",
      "Zjfss": "-28647.00",
      "Syje": "47391.15",
      "Zqyjlx": "0.00000000",
      "Jsrq": "20260114",
      "Mmlb_ex": "B",
      "Mmlb_bs": "B"
    },
    {
      "Cjrq": "20260114",
      "Cjsj": "130910",
      "Cjsj2": "130910",
      "Zqdm": "920021",
      "Zqmc": "流金科技",
      "Mmsm": "证券买入",
      "Cjjg": "13.3500",
      "Cjsl": "3719",
      "Cjje": "49648.65",
      "Sxf": "34.75",
      "Yhs": "0.00",
      "Ghf": "0.00",
      "Zjye": "76038.15",
      "Gfye": "4857",
      "Market": "B",
      "Cjbh": "02629573",
      "Wtbh": "1715544",
      "Gddm": "0917534836",
      "Dwc": "",
      "Qqhs": null,
      "Mmlb": "B",
      "Htxh": "B2500276",
      "Wtxh": "1715544",
      "Cpbm": "",
      "Cjxh": "02629573",
      "Wtsl": "3719",
      "Wtjg": "13.4900",
      "Gfbcye": "4857",
      "Jsxf": "28.04",
      "Qsf": "0.00",
      "Jygf": "0.00",
      "Jsf": "0.00",
      "Zgf": "0.00",
      "Qtf": "0.00",
      "Qtfy": "0.00",
      "Zjfss": "-49683.40",
      "Syje": "76038.15",
      "Zqyjlx": "0.00000000",
      "Jsrq": "20260114",
      "Mmlb_ex": "B",
      "Mmlb_bs": "B"
    },
    {
      "Cjrq": "20260114",
      "Cjsj": "130841",
      "Cjsj2": "130841",
      "Zqdm": "002792",
      "Zqmc": "通宇通讯",
      "Mmsm": "证券卖出",
      "Cjjg": "64.4000",
      "Cjsl": "700",
      "Cjje": "45080.00",
      "Sxf": "11.27",
      "Yhs": "22.54",
      "Ghf": "0.00",
      "Zjye": "125721.55",
      "Gfye": "0",
      "Market": "SA",
      "Cjbh": "0102000072005756",
      "Wtbh": "1707429",
      "Gddm": "0917534836",
      "Dwc": "",
      "Qqhs": null,
      "Mmlb": "S",
      "Htxh": "0801707429",
      "Wtxh": "1707429",
      "Cpbm": "",
      "Cjxh": "0102000072005756",
      "Wtsl": "700",
      "Wtjg": "64.4000",
      "Gfbcye": "0",
      "Jsxf": "8.38",
      "Qsf": "0.00",
      "Jygf": "0.00",
      "Jsf": "0.00",
      "Zgf": "0.00",
      "Qtf": "0.00",
      "Qtfy": "0.00",
      "Zjfss": "45046.19",
      "Syje": "125721.55",
      "Zqyjlx": "0.00000000",
      "Jsrq": "20260114",
      "Mmlb_ex": "S",
      "Mmlb_bs": "S"
    },
    {
      "Cjrq": "20260114",
      "Cjsj": "130003",
      "Cjsj2": "130003",
      "Zqdm": "000547",
      "Zqmc": "航天发展",
      "Mmsm": "证券卖出",
      "Cjjg": "33.9410",
      "Cjsl": "1000",
      "Cjje": "33941.00",
      "Sxf": "8.49",
      "Yhs": "16.97",
      "Ghf": "0.00",
      "Zjye": "80675.36",
      "Gfye": "0",
      "Market": "SA",
      "Cjbh": "0103000062415323",
      "Wtbh": "1600741",
      "Gddm": "0917534836",
      "Dwc": "",
      "Qqhs": null,
      "Mmlb": "S",
      "Htxh": "0801600741",
      "Wtxh": "1600741",
      "Cpbm": "",
      "Cjxh": "0103000062415323",
      "Wtsl": "1000",
      "Wtjg": "33.9400",
      "Gfbcye": "0",
      "Jsxf": "6.30",
      "Qsf": "0.00",
      "Jygf": "0.00",
      "Jsf": "0.00",
      "Zgf": "0.00",
      "Qtf": "0.00",
      "Qtfy": "0.00",
      "Zjfss": "33915.54",
      "Syje": "80675.36",
      "Zqyjlx": "0.00000000",
      "Jsrq": "20260114",
      "Mmlb_ex": "S",
      "Mmlb_bs": "S"
    },
    {
      "Cjrq": "20260114",
      "Cjsj": "130243",
      "Cjsj2": "130243",
      "Zqdm": "920021",
      "Zqmc": "流金科技",
      "Mmsm": "证券买入",
      "Cjjg": "13.5700",
      "Cjsl": "1138",
      "Cjje": "15442.66",
      "Sxf": "10.81",
      "Yhs": "0.00",
      "Ghf": "0.00",
      "Zjye": "46759.82",
      "Gfye": "1138",
      "Market": "B",
      "Cjbh": "02487759",
      "Wtbh": "1566744",
      "Gddm": "0917534836",
      "Dwc": "",
      "Qqhs": null,
      "Mmlb": "B",
      "Htxh": "B2500255",
      "Wtxh": "1566744",
      "Cpbm": "",
      "Cjxh": "02487759",
      "Wtsl": "1138",
      "Wtjg": "13.5700",
      "Gfbcye": "1138",
      "Jsxf": "8.73",
      "Qsf": "0.00",
      "Jygf": "0.00",
      "Jsf": "0.00",
      "Zgf": "0.00",
      "Qtf": "0.00",
      "Qtfy": "0.00",
      "Zjfss": "-15453.47",
      "Syje": "46759.82",
      "Zqyjlx": "0.00000000",
      "Jsrq": "20260114",
      "Mmlb_ex": "B",
      "Mmlb_bs": "B"
    },
    {
      "Cjrq": "20260114",
      "Cjsj": "111538",
      "Cjsj2": "111538",
      "Zqdm": "300010",
      "Zqmc": "豆神教育",
      "Mmsm": "证券买入",
      "Cjjg": "9.2600",
      "Cjsl": "1500",
      "Cjje": "13890.00",
      "Sxf": "5.00",
      "Yhs": "0.00",
      "Ghf": "0.00",
      "Zjye": "62213.29",
      "Gfye": "9000",
      "Market": "SA",
      "Cjbh": "0104000059306020",
      "Wtbh": "1473102",
      "Gddm": "0917534836",
      "Dwc": "",
      "Qqhs": null,
      "Mmlb": "B",
      "Htxh": "0801473102",
      "Wtxh": "1473102",
      "Cpbm": "",
      "Cjxh": "0104000059306020",
      "Wtsl": "1500",
      "Wtjg": "9.2600",
      "Gfbcye": "9000",
      "Jsxf": "4.11",
      "Qsf": "0.00",
      "Jygf": "0.00",
      "Jsf": "0.00",
      "Zgf": "0.00",
      "Qtf": "0.00",
      "Qtfy": "0.00",
      "Zjfss": "-13895.00",
      "Syje": "62213.29",
      "Zqyjlx": "0.00000000",
      "Jsrq": "20260114",
      "Mmlb_ex": "B",
      "Mmlb_bs": "B"
    },
    {
      "Cjrq": "20260114",
      "Cjsj": "111211",
      "Cjsj2": "111211",
      "Zqdm": "300010",
      "Zqmc": "豆神教育",
      "Mmsm": "证券买入",
      "Cjjg": "9.2500",
      "Cjsl": "2200",
      "Cjje": "20350.00",
      "Sxf": "5.09",
      "Yhs": "0.00",
      "Ghf": "0.00",
      "Zjye": "76108.29",
      "Gfye": "7500",
      "Market": "SA",
      "Cjbh": "0104000058374178",
      "Wtbh": "1453837",
      "Gddm": "0917534836",
      "Dwc": "",
      "Qqhs": null,
      "Mmlb": "B",
      "Htxh": "0801453837",
      "Wtxh": "1453837",
      "Cpbm": "",
      "Cjxh": "0104000058374178",
      "Wtsl": "2200",
      "Wtjg": "9.2500",
      "Gfbcye": "7500",
      "Jsxf": "3.78",
      "Qsf": "0.00",
      "Jygf": "0.00",
      "Jsf": "0.00",
      "Zgf": "0.00",
      "Qtf": "0.00",
      "Qtfy": "0.00",
      "Zjfss": "-20355.09",
      "Syje": "76108.29",
      "Zqyjlx": "0.00000000",
      "Jsrq": "20260114",
      "Mmlb_ex": "B",
      "Mmlb_bs": "B"
    },
    {
      "Cjrq": "20260114",
      "Cjsj": "110757",
      "Cjsj2": "110757",
      "Zqdm": "000547",
      "Zqmc": "航天发展",
      "Mmsm": "证券卖出",
      "Cjjg": "33.8100",
      "Cjsl": "900",
      "Cjje": "30429.00",
      "Sxf": "7.61",
      "Yhs": "15.21",
      "Ghf": "0.00",
      "Zjye": "96463.38",
      "Gfye": "1000",
      "Market": "SA",
      "Cjbh": "0103000055788020",
      "Wtbh": "1430112",
      "Gddm": "0917534836",
      "Dwc": "20260114|2772040",
      "Qqhs": null,
      "Mmlb": "S",
      "Htxh": "0801430112",
      "Wtxh": "1430112",
      "Cpbm": "",
      "Cjxh": "0103000055788020",
      "Wtsl": "900",
      "Wtjg": "33.8100",
      "Gfbcye": "1000",
      "Jsxf": "5.66",
      "Qsf": "0.00",
      "Jygf": "0.00",
      "Jsf": "0.00",
      "Zgf": "0.00",
      "Qtf": "0.00",
      "Qtfy": "0.00",
      "Zjfss": "30406.18",
      "Syje": "96463.38",
      "Zqyjlx": "0.00000000",
      "Jsrq": "20260114",
      "Mmlb_ex": "S",
      "Mmlb_bs": "S"
    }
  ]
}